Workbook

Sheet in
A1: scopus_id | B1: doi | C1: title | D1: journal | E1: publication_year | F1: keywords | G1: abstract | H1: corresponding_author_country | I1: cited_by_count | J1: policy_claim_via_terms | K1: v1_llm_policy_claim | L1: DB review | M1: DB notes | N1: EC review | O1: EC notes | P1: DB notes | Q1: v1.9_updated LLM prompt claim | T1: MW review | U1: MW notes | W1: llm_policy_claim
A2: SCOPUS_ID:78650633722 | B2: 10.1093/aje/kwq345 | C2: Adult body size, hormone receptor status, and premenopausal breast cancer risk in a multiethnic population | D2: American Journal of Epidemiology | E2: 2011 | F2: ['African Americans', 'body size', 'breast neoplasms', 'Hispanic Americans', 'premenopause', 'receptors, estrogen', 'receptors, progesterone'] | G2: Large body size has been associated with a reduced risk of premenopausal breast cancer in non-Hispanic white women. Data on other racial/ethnic populations are limited. The authors examined the association between premenopausal breast cancer risk and adult body size in 672 cases and 808 controls aged â‰¥35 years from a population-based case-control study conducted in 1995-2004 in the San Francisco Bay Area (Hispanics: 375 cases, 483 controls; African Americans: 154 cases, 160 controls; non-Hispanic whites: 143 cases, 165 controls). Multivariate adjusted odds ratios and 95% confidence intervals were calculated using unconditional logistic regression. Height was associated with increased breast cancer risk (highest vs. lowest quartile: odds ratio = 1.77, 95% confidence interval: 1.23, 2.53; Ptrend < 0.01); the association did not vary by hormone receptor status or race/ethnicity. Body mass index (measured as weight (kg) divided by height (m) squared) was inversely associated with risk in all 3 racial/ethnic groups, but only for estrogen receptor- and progesterone receptor-positive tumors (body mass index â‰¥30 vs. <25: odds ratio = 0.42; 95% confidence interval: 0.29, 0.61). Other body size measures (current weight, body build, adult weight gain, young adult weight and body mass index, waist circumference, and waist-to-height ratio) were similarly inversely associated with risk of estrogen receptor- and progesterone receptor-positive breast cancer but not estrogen receptor- and progesterone receptor-negative disease. Despite racial/ethnic differences in body size, inverse associations were similar across the 3 racial/ethnic groups when stratified by hormone receptor status. Â© 2010 The Author. | H2: United States | I2: 59 | J2: FALSE | K2: FALSE | L2: FALSE | N2: FALSE | Q2: FALSE | R2: =IF(Q2<>N2,"!!!","") | W2: FALSE
A3: SCOPUS_ID:0032978484 | B3: 10.2105/AJPH.89.2.171 | C3: The impact of physician bonuses, enhanced fees, and feedback on childhood immunization coverage rates | D3: American Journal of Public Health | E3: 1999 | F3: [] | G3: Objectives. The purpose of this study was to examine the effects on immunization coverage of 3 incentives for physicians - a cash bonus for practice-wide increases, enhanced fee for service, and feedback. Methods. Incentives were applied at 4-month intervals over 1 year among 60 inner-city office-based pediatricians. At each interval, charts of 50 randomly selected children between 3 and 35 months of age were reviewed per physician. Results. The percentage of children who were up to date for diphtheria, tetanus, and pertussis and Haemophilus influenzae type b; polio; and measles-mumps- rubella immunization in the study's bonus group improved by 25.3 percentage points (P < .01). No significant changes occurred in the other groups. However, percentage of immunizations received outside the participating practice also increased significantly in the bonus group (P < .0.1). Levels of missed opportunities to immunize were high in all groups and did hot change over time. Physicians' knowledge of contraindications was low. Conclusions: Bonuses sharply and rapidly increased immunization coverage in medical records. However, much of the increase was the result of better documentation. A bonus is a powerful incentive, but more structure or education may be necessary to achieve the desired results. | H3: United States | I3: 139 | J3: FALSE | K3: TRUE | L3: FALSE | M3: marginal | N3: FALSE | O3: The final statement is strong but not really a policy recommendation - hard one. | P3: agree - may be intrinsic limit of LLMs | Q3: FALSE | R3: =IF(Q3<>N3,"!!!","") | W3: FALSE
A4: SCOPUS_ID:0032931075 | B4: 10.1093/oxfordjournals.aje.a009723 | C4: Prospective study of diet and ovarian cancer | D4: American Journal of Epidemiology | E4: 1999 | F4: ['Diet', 'Nutrition', 'Ovarian neoplasms', 'Postmenopausal', 'Prospective studies', 'Risk', 'Risk factors'] | G4: Evidence on dietary risk factors for ovarian cancer is inconsistent, but some studies have suggested positive associations with dietary fat, lactose, and cholesterol and negative associations with green and yellow vegetable intake. By using information from the Iowa Women's Health Study, the authors investigated the association of epithelial ovarian cancer with dietary factors in a prospective study of 29,083 postmenopausal women. Dietary information was ascertained via a food frequency questionnaire mailed to participants in 1986. During 10 years of follow-up (1986-1995), 139 of the women developed incident epithelial ovarian cancer. Incidence of the disease was not associated with dietary fat intake. Lactose and cholesterol showed moderately elevated risks. Multivariable-adjusted relative risks for the lowest to highest quartiles of lactose intake were 1.00, 1.38, 1.25, and 1.60 (p for trend = 0.12). For cholesterol, the corresponding values were 1.00, 1.34, 1.86, and 1.55 (p for trend = 0.06). Consumption of eggs was also associated with an increased risk of ovarian cancer. Multivariable-adjusted relative risks for increasing frequency of egg consumption were 1.00 (<1/week), 1.12 (1/week), 2.04 (2-4/week), and 1.81 (>4/week) (p for trend = 0.04). Total vegetable intake was modestly and inversely associated with the risk of ovarian cancer (p for trend = 0.21). Green leafy vegetable intake was more strongly associated with a decreased risk: multivariable-adjusted relative risks for the lowest to highest intake levels were 1.00, 0.80, 0.87, and 0.44 (p = 0.01). These findings are generally in agreement with the results from previous, mostly case-control studies of diet and epithelial ovarian cancer. | H4: United States | I4: 201 | J4: FALSE | K4: FALSE | L4: FALSE | N4: FALSE | Q4: FALSE | R4: =IF(Q4<>N4,"!!!","") | W4: FALSE
A5: SCOPUS_ID:85066260594 | B5: 10.1016/S2468-2667(19)30018-0 | C5: Geospatial, racial, and educational variation in firearm mortality in the USA, Mexico, Brazil, and Colombia, 1990â€“2015: a comparative analysis of vital statistics data | D5: The Lancet Public Health | E5: 2019 | F5: [] | G5: Background: Firearm mortality is a leading, and largely avoidable, cause of death in the USA, Mexico, Brazil, and Colombia. We aimed to assess the changes over time and demographic determinants of firearm deaths in these four countries between 1990 and 2015. Methods: In this comparative analysis of firearm mortality, we examined national vital statistics data from 1990â€“2015 from four publicly available data repositories in the USA, Mexico, Brazil, and Colombia. We extracted medically-certified deaths and underlying population denominators to calculate the age-specific and sex-specific firearm deaths and the risk of firearm mortality at the national and subnational level, by education for all four countries, and by race or ethnicity for the USA and Brazil. Analyses were stratified by intent (homicide, suicide, unintentional, or undetermined). We quantified avoidable mortality for each country using the lowest number of subnational age-specific and period-specific death rates. Findings: Between 1990 and 2015, 106Â·3 million medically-certified deaths were recorded, including 2 472 000 firearm deaths, of which 851 000 occurred in the USA, 272 000 in Mexico, 855 000 in Brazil, and 494 000 in Colombia. Homicides accounted for most of the firearm deaths in Mexico (225 000 [82Â·7%]), Colombia (463 000 [93Â·8%]), and Brazil (766 000 [89Â·5%]). Suicide accounted for more than half of all firearm deaths in the USA (479 000 [56Â·3%]). In each country, firearm mortality was highest among men aged 15â€“34 years, accounting for up to half of the total risk of death in that age group. During the study period, firearm mortality risks increased in Mexico and Brazil but decreased in the USA and Colombia, with marked national and subnational geographical variation. Young men with low educational attainment were at increased risk of firearm homicide in all four countries, and in the USA and Brazil, black and brown men, respectively, were at the highest risk. The risk of firearm homicide was 14 times higher in black men in the USA aged 25â€“34 years with low educational attainment than comparably-educated white men (1Â·52% [99% CI 1Â·50â€“1Â·54] vs 0Â·11% [0Â·10â€“0Â·12]), and up to four times higher than in comparably-educated men in Brazil, Colombia, and Mexico. In the USA, the risk of firearm homicide was more than 30 times higher in black men with post-secondary education than comparably educated white men. If countries could achieve the same firearm mortality rates nationally as in their lowest-burden states, 1 777 800 firearm deaths at all ages and in both sexes could be avoided, including 1 028 000 deaths in men aged 15â€“34 years. Interpretation: Firearm mortality in the USA, Mexico, Brazil, and Colombia is highest among young adult men, and is strongly associated with race and ethnicity, and low education levels. Reductions in firearm deaths would improve life expectancy, particularly for black men in the USA, and would reduce racial and educational disparities in mortality. Funding: Canadian Institutes of Health Research and the University of Toronto Connaught Global Challenge. | H5: Mexico | I5: 26 | J5: FALSE | K5: TRUE | L5: FALSE | M5: marginal | N5: FALSE | O5: I think it is worded carefully ('could'). Is the use of conditional something we could add to our algorithm? | P5: I don't think so for the terms approach. For the analysis in which study design is correlated with claims, we can manually screen the "made policy claim" group. | Q5: FALSE | R5: =IF(Q5<>N5,"!!!","") | W5: TRUE
A6: SCOPUS_ID:84895890934 | B6: 10.1093/aje/kwt327 | C6: Trends in alcohol and other drugs detected in fatally injured drivers in the United States, 1999-2010 | D6: American Journal of Epidemiology | E6: 2014 | F6: ['accidents', 'alcohol consumption', 'cannabinoids', 'drug users', 'motor vehicles', 'prescription drugs', 'safety', 'traffic'] | G6: Drugged driving is a safety issue of increasing public concern. Using data from the Fatality Analysis Reporting System for 1999-2010, we assessed trends in alcohol and other drugs detected in drivers who were killed within 1 hour of a motor vehicle crash in 6 US states (California, Hawaii, Illinois, New Hampshire, Rhode Island, and West Virginia) that routinely performed toxicological testing on drivers involved in such crashes. Of the 23,591 drivers studied, 39.7% tested positive for alcohol and 24.8% for other drugs. During the study period, the prevalence of positive results for nonalcohol drugs rose from 16.6% in 1999 to 28.3% in 2010 (Z =-10.19, P < 0.0001), whereas the prevalence of positive results for alcohol remained stable. The most commonly detected nonalcohol drug was cannabinol, the prevalence of which increased from 4.2% in 1999 to 12.2% in 2010 (Z =-13.63, P < 0.0001). The increase in the prevalence of nonalcohol drugs was observed in all age groups and both sexes. These results indicate that nonalcohol drugs, particularly marijuana, are increasingly detected in fatally injured drivers. Â© 2014 The Author. | H6: United States | I6: 168 | J6: FALSE | K6: FALSE | L6: FALSE | N6: FALSE | Q6: FALSE | R6: =IF(Q6<>N6,"!!!","") | W6: FALSE
A7: SCOPUS_ID:84912129265 | B7: 10.1016/j.amepre.2014.08.009 | C7: Adult vaccination disparities among foreign-born populations in the u.s., 2012 | D7: American Journal of Preventive Medicine | E7: 2014 | F7: [] | G7: Background Foreign-born persons are considered at higher risk of undervaccination and exposure to many vaccine-preventable diseases. Information on vaccination coverage among foreign-born populations is limited. | H7: United States | I7: 65 | J7: FALSE | K7: FALSE | L7: FALSE | M7: n/a abstract | N7: FALSE | O7: I dont know how frequent that is, but we might want to remove these? | P7: edited scripts to exclude abstracts <100 words | Q7: FALSE | R7: =IF(Q7<>N7,"!!!","") | W7: FALSE
A8: SCOPUS_ID:69549088896 | B8: 10.1097/EDE.0b013e3181ad5522 | C8: Extreme high temperatures and hospital admissions for respiratory and cardiovascular diseases | D8: Epidemiology | E8: 2009 | F8: [] | G8: BACKGROUND: Although the association of high temperatures with mortality is well-documented, the association with morbidity has seldom been examined. We assessed the potential impact of hot weather on hospital admissions due to cardiovascular and respiratory diseases in New York City. We also explored whether the weather-disease relationship varies with socio-demographic variables. METHOD: We investigated effects of temperature and humidity on health by linking the daily cardiovascular and respiratory hospitalization counts with meteorologic conditions during summer, 1991-2004. We used daily mean temperature, mean apparent temperature, and 3-day moving average of apparent temperature as the exposure indicators. Threshold effects for health risks of meteorologic conditions were assessed by log-linear threshold models, after controlling for ozone, day of week, holidays, and long-term trend. Stratified analyses were used to evaluate temperature-demographic interactions. RESULTS: For all 3 exposure indicators, each degree C above the threshold of the temperature-health effect curve (29Â°C-36Â°C) was associated with a 2.7%-3.1% increase in same-day hospitalizations due to respiratory diseases, and an increase of 1.4%-3.6% in lagged hospitalizations due to cardiovascular diseases. These increases for respiratory admissions were greater for Hispanic persons (6.1%/Â°C) and the elderly (4.7%/Â°C). At high temperatures, admission rates increased for chronic airway obstruction, asthma, ischemic heart disease, and cardiac dysrhythmias, but decreased for hypertension and heart failure. CONCLUSIONS: Extreme high temperature appears to increase hospital admissions for cardiovascular and respiratory disorders in New York City. Elderly and Hispanic residents may be particularly vulnerable to the temperature effects on respiratory illnesses. Â© 2009 Lippincott Williams & Wilkins, Inc. | H8: United States | I8: 366 | J8: FALSE | K8: FALSE | L8: FALSE | N8: FALSE | Q8: FALSE | R8: =IF(Q8<>N8,"!!!","") | W8: FALSE
A9: SCOPUS_ID:85088828588 | B9: 10.1007/s10654-020-00665-w | C9: Body mass index in young adulthood and risk of subsequent dementia at different levels of intelligence and education in Danish men | D9: European Journal of Epidemiology | E9: 2020 | F9: ['Body mass index', 'Cohort study', 'Dementia', 'Intelligence'] | G9: The risk of dementia seems to be established already early in life, which leads to the question if overweight early in life is an important risk factor for dementia as it appears to be later in life. We examined the association between body mass index (BMI) at entry to adult life and subsequent risk of dementia in men and assessed whether the relationship differed by levels of intelligence and education. The study population consisted of 377,598 Danish men born 1939â€“1959 with measures of height, weight, intelligence test score (ITS), and educational level (EL) at conscript board examinations around the age of 19Â years. Dementia outcomes were obtained from National Patient and Prescription Registries between 1969 and 2016. The association between BMI and dementia was analysed using Cox proportional hazard regression including interactions between BMI and ITS and EL, respectively. During the follow-up through age 77 years, 6144 (1.6%) developed dementia. The frequency was highest in men with lowest BMI, lowest ITS and lowest EL. Young adult BMI below the mean of 21.8Â kg/m2 was inversely associated with subsequent dementia, whereas there was no association with higher levels of BMI. Adjustment for young adult ITS and EL attenuated the risk estimates slightly, and interaction analyses showed that the shape of the association between BMI and dementia was unaffected by the levels of ITS and EL. Regardless of levels of ITS and EL, young adult BMI below the mean is inversely associated with subsequent dementia, whereas there is no association with higher levels of BMI. | H9: Denmark | I9: 5 | J9: FALSE | K9: FALSE | L9: FALSE | N9: FALSE | Q9: FALSE | R9: =IF(Q9<>N9,"!!!","") | W9: FALSE
A10: SCOPUS_ID:85054204629 | B10: 10.1093/aje/kwy091 | C10: Ramadan Exposure in Utero and Child Mortality in Burkina Faso: Analysis of a Population-Based Cohort Including 41,025 Children | D10: American Journal of Epidemiology | E10: 2018 | F10: ['child mortality', 'difference in differences', 'population-based cohort', 'pregnancy', 'prenatal exposure delayed effects', 'Ramadan', 'sub-Saharan Africa'] | G10: Ramadan exposure in utero can be regarded as a natural experiment with which to study how nutritional conditions in utero influence susceptibility to disease later in life. We analyzed data from rural Burkina Faso on 41,025 children born between 1993 and 2012, of whom 25,093 were born to Muslim mothers. Ramadan exposure was assigned on the basis of overlap between Ramadan dates and gestation, creating 7 exclusive categories. We used proportional hazards regression with difference-in-differences analysis to estimate the association between Ramadan exposure at different gestational ages and mortality among children under 5 years of age. Under-5 mortality was 32 deaths per 1,000 child-years. Under-5 mortality among Muslims was 15% higher than that among non-Muslims (P < 0.001). In the difference-in-differences analysis, the occurrence of Ramadan during conception or the first or second trimester was associated with higher under-5 mortality rates among Muslims only. The mortality rates of children born to Muslim mothers were 33%, 29%, and 22% higher when Ramadan occurred during conception, the first trimester, and the second trimester, respectively, compared with children of non-Muslim mothers born at the same time (P = 0.01, P < 0.001, and P = 0.007). Having a Muslim mother was not associated with mortality when the child was not exposed to Ramadan, born during Ramadan, or exposed during the third trimester. Observance of Ramadan during early pregnancy can have detrimental consequences for the future health of the unborn child. | H10: Germany | I10: 24 | J10: FALSE | K10: FALSE | L10: FALSE | M10: overly bold conclusion, but not a policy claims | N10: FALSE | O10: Agreed, maybe the tense is important here - can vs could. | P10: good, in which case all agree | Q10: FALSE | R10: =IF(Q10<>N10,"!!!","") | W10: FALSE
A11: SCOPUS_ID:84946734426 | B11: 10.2105/AJPH.2015.302611 | C11: Health care disparities in the post-affordable care act era | D11: American Journal of Public Health | E11: 2015 | F11: [] | G11: Disparities in health care have been targeted for elimination by federal agencies and professional organizations, including the American Public Health Association. Although the Affordable Care Act (ACA) provides a valuable first step in reducing the disparities gap, progress is contingent upon whether opportunities in the ACA help or hinder populations at risk for impaired health and limited access to medical care. | H11: United States | I11: 73 | J11: FALSE | K11: FALSE | L11: FALSE | M11: n/a abstract | N11: FALSE | Q11: FALSE | R11: =IF(Q11<>N11,"!!!","") | W11: TRUE
A12: SCOPUS_ID:45549105637 | B12: 10.2105/AJPH.2007.121137 | C12: Prevalence of chronic diseases and multimorbidity among the elderly population in Sweden | D12: American Journal of Public Health | E12: 2008 | F12: [] | G12: We explored the role of age, gender, and socioeconomic status in the occurrence of chronic diseases and multimorbidity in 1099 elderly participants in the Kungsholmen Project. Cardiovascular and mental diseases were the most common chronic disorders. Of the participants, 55% had multimorbidity. Advanced age, female gender, and lower education were independently associated with a more than 50% increased risk for multimorbidity. Multimorbidity is the most common clinical picture of the elderly and may be increased by unhealthy behaviors linked to education. | H12: Sweden | I12: 312 | J12: FALSE | K12: FALSE | L12: FALSE | N12: FALSE | Q12: FALSE | R12: =IF(Q12<>N12,"!!!","") | W12: FALSE
A13: SCOPUS_ID:0025121054 | B13: 10.2105/AJPH.80.9.1101 | C13: The effects of workplace health promotion on absenteeism and employment costs in a large industrial population | D13: American Journal of Public Health | E13: 1990 | F13: [] | G13: We evaluated the impact of a comprehensive workplace health promotion program on absences among full-time employees in a large, multi-location, diversified industrial company. A pretest-posttest control group design was used to study 41 intervention sites and 19 control sites with 29,315 and 14,573 hourly employees, respectively. Blue-collar employees at intervention sites experienced an 14.0 percent decline in disability days over two years versus a 5.8 percent decline at control sites. This resulted in a net difference of 11,726 fewer disability days over two years at program sites compared with non-program sites. Savings due to lower disability costs at intervention sites offset program costs in the first year, and provided a return of $2.05 for every dollar invested in the program by the end of the second year. These results suggest that comprehensive workplace health promotion programs can reduce disability days among blue collar employees and provide a good return on investiment. | H13: United States | I13: 161 | J13: FALSE | K13: FALSE | L13: FALSE | N13: FALSE | Q13: FALSE | R13: =IF(Q13<>N13,"!!!","") | W13: FALSE
A14: SCOPUS_ID:84875598366 | B14: 10.1093/ije/dys214 | C14: Consistently high estimates for the proportion of human exposure to malaria vector populations occurring indoors in rural Africa | D14: International Journal of Epidemiology | E14: 2013 | F14: ['Behavior', 'Exposure', 'Malaria', 'Plasmodium', 'Transmission', 'Vector'] | G14: Background Insecticide-treated nets (ITNs) and indoor residual spraying (IRS) are highly effective tools for controlling malaria transmission in Africa because the most important vectors, from the Anopheles gambiae complex and the A. funestus group, usually prefer biting humans indoors at night. Methods Matched surveys of mosquito and human behaviour from six rural sites in Burkina Faso, Tanzania, Zambia, and Kenya, with ITN use ranging from 0.2 to 82.5, were used to calculate the proportion of human exposure to An. gambiae sensu lato and An. funestus s.l. that occurs indoors (Ï€i), as an indicator of the upper limit of personal protection that indoor vector control measures can provide. This quantity was also estimated through use of a simplified binary analysis (Ï€iB) so that the proportions of mosquitoes caught indoors (Pi), and between the first and last hours at which most people are indoors (Pfl) could also be calculated as underlying indicators of feeding by mosquitoes indoors or at night, respectively. Results The vast majority of human exposure to Anopheles bites occurred indoors (iB 0.79-1.00). Neither An. gambiae s.l. nor An. funestus s.l. strongly preferred feeding indoors (Pi 0.40-0.63 and 0.22-0.69, respectively), but they overwhelmingly preferred feeding at times when most humans were indoors (Pfl 0.78-1.00 and 0.86-1.00, respectively). Conclusions These quantitative summaries of behavioural interactions between humans and mosquitoes constitute a remarkably consistent benchmark with which future observations of vector behaviour can be compared. Longitudinal monitoring of these quantities is vital to evaluate the effectiveness of ITNs and IRS and the need for complementary measures that target vectors outdoors. Published by Oxford University Press on behalf of the International Epidemiological Association. Â© The Author 2013; all rights reserved. | H14: Burkina Faso | I14: 129 | J14: FALSE | K14: TRUE | L14: FALSE | M14: marginal - research is called for not policy? | N14: FALSE | O14: Yes research recommendation, not sure how to filter those, maybe iterations of further research needed | P14: I added to the LLM prompt that research recommendations don't count as policy recommendations; they might not be able to distinguish. New prompt=FALSE | Q14: FALSE | R14: =IF(Q14<>N14,"!!!","") | W14: FALSE
A15: SCOPUS_ID:85045210606 | B15: 10.1016/j.amepre.2018.01.008 | C15: Changes in School Food Preparation Methods Result in Healthier Cafeteria Lunches in Elementary Schools | D15: American Journal of Preventive Medicine | E15: 2018 | F15: [] | G15: Introduction: The purpose of this study is to examine the impact of a districtwide food best practices and preparation changes in elementary schools lunches, implemented as part of the LiveWell@School childhood obesity program, funded by LiveWell Colorado/Kaiser Permanente Community Health Initiative. Methods: Longitudinal study examining how school changes in best practices for food preparation impacted the types of side items offered from 2009 to 2015 in elementary school cafeterias in a high-need school district in southern Colorado. Specifically, this study examined changes in side items (fruits, vegetables, potatoes, breads, and desserts). In Phase 1 (2009â€“2010), baseline data were collected. During Phase 2 (2010â€“2011), breaded and processed foods (e.g., frozen nuggets, pre-packaged pizza) were removed and school chefs were trained on scratch cooking methods. Phase 3 (2011â€“2012) saw an increased use of fresh/frozen fruits and vegetables after a new commodity order. During Phase 4 (2013â€“2015), chef consulting and training took place. The frequency of side offerings was tracked across phases. Analyses were completed in Fall 2016. Because of limited sample sizes, data from Phases 2 to 4 (intervention phases) were combined for potatoes and desserts. Descriptive statistics were calculated. After adjusting for length of time for each phase, Pearson chi-square tests were conducted to examine changes in offerings of side items by phase. Results: Fresh fruit offerings increased and canned fruit decreased in Phases 1â€“4 (p=0.001). A significant difference was observed for vegetables (p=0.001), with raw and steamed vegetables increasing and canned vegetables decreasing from Phase 1 to 4. Fresh potatoes (low in sodium) increased and fried potatoes (high in sodium) decreased from Phase 1 to Phases 2â€“4 (p=0.001). Breads were eliminated entirely in Phase 2, and dessert changes were not significant (p=0.927). Conclusions: This approach to promoting healthier lunch sides is a promising paradigm for improving elementary cafeteria food offerings. Supplement information: This article is part of a supplement entitled Building Thriving Communities Through Comprehensive Community Health Initiatives, which is sponsored by Kaiser Permanente, Community Health. | H15: United States | I15: 8 | J15: FALSE | K15: FALSE | L15: FALSE | N15: FALSE | Q15: FALSE | R15: =IF(Q15<>N15,"!!!","") | W15: FALSE
A16: SCOPUS_ID:0031194498 | B16: 10.1006/pmed.1997.0151 | C16: Epidemiology of low total plasma cholesterol concentration among young adults: The CARDIA study | D16: Preventive Medicine | E16: 1997 | F16: ['Cholesterol', 'Risk factors', 'Young adults'] | G16: Background. Data on stability of plasma total cholesterol levels and its determinants among young adults are lacking. Knowledge of factors associated with low levels of plasma total cholesterol during young adulthood may help clarify the nature of associations between hypocholesterolemia and health or illness. Methods. Tracking of plasma total cholesterol was investigated using data from the baseline (1985-1986), Year 5 (1990-1991), and Year 7 (1992- 1993) examinations of the Coronary Artery Risk Development in Young Adults Study. Lifestyle (including dietary), physiological, medical, and psychological correlates of plasma total cholesterol were examined cross- sectionally at baseline using ANCOVA and multivariate logistic regression. The attributes of participants with persistently low plasma total cholesterol level after 7 years (i.e., remaining below the 10th percentile of sex- and race-specific distributions) were also examined. Results. The cohort in this analysis comprised 720 black men, 922 white men, 899 black women, and 944 white women who were between the ages of 18 and 30 years at baseline. Between 44 and 52% of those with plasma total cholesterol levels below the 10th percentile remained below the same percentile 7 years later. Among black men, a difference of 1 SD in age [3.7 years; odds ratio (OR) = 0.69; 95% CI = 0.52-0.91] and a difference of 1 SD in systolic blood pressure (10.5 mm Hg; OR = 0.73; 95% CI = 0.54-0.97) were independently associated with lower odds, respectively, of being in the lowest 10th percentile of the plasma total cholesterol distribution. Also among black men, current smoking and more calories from carbohydrates were associated with nonsignificantly higher odds of low total cholesterol level. Among white men, a 1 SD older age (3.4 years; OR = 0.78; 95% CI = 0.61-1.00) and a 1 SD higher physical fitness (118 see; OR = 1.41; 95% CI = 1.09-1.82) predicted lower and higher odds, respectively, of low plasma total cholesterol. Among black women, a 1 SD difference in albumin (0.3 g/dL; OR = 0.80; 95% CI = 0.63-1.03) was related to lower odds of low plasma total cholesterol. Among white women, the factors independently associated with low plasma total cholesterol were body mass index (OR for a difference in 4.0 kg/m2 = 0.73; 95% CI = 0.54-1.00) and Î³-glutamyl transferase (OR for an increase in 9.6 IU/L = 0.41; 95% CI = 0.18-0.93). The independent predictive factors of stably low total cholesterol levels were age and uric acid among black men (both inversely related) and age, Framingham Type A Behavior (inversely), and calories from carbohydrates (positively related) among white men. Conclusion: Young adults with low plasma total cholesterol level have characteristics generally associated with good cardiovascular health. However, adverse attributes such as current cigarette smoking (notably among black men) may confound future associations between low total cholesterol and disease. | H16: United States | I16: 9 | J16: FALSE | K16: FALSE | L16: FALSE | N16: FALSE | Q16: FALSE | R16: =IF(Q16<>N16,"!!!","") | W16: FALSE
A17: SCOPUS_ID:0029924623 | B17: 10.1097/00001648-199605000-00011 | C17: Silica and aluminum in drinking water and cognitive impairment in the elderly | D17: Epidemiology | E17: 1996 | F17: ['aluminum', "Alzheimer's disease", 'cognitive impairment', 'dementia', 'drinking water', 'elderly', 'silicon'] | G17: We studied the relation between silica and aluminum levels in drinking water and the risk of cognitive impairment using data from a population- based survey of 3,777 French subjects age 65 years and older. We also studied the effect of pH and the concentrations of calcium, magnesium, fluorine, zinc, copper, and iron. We used a mixed effects logistic regression adjusting for age, sex, educational level, and occupation of the subjects. We confirmed the inverse relation previously found between calcium level and cognitive impairment. We found no important association between cognitive impairment and fluorine, magnesium, iron, copper, or zinc. The association between cognitive impairment and aluminum depended on the pH and the concentration of silica: high levels of aluminum appeared to have a deleterious effect when the silica concentration was low, but there was a protective effect when the pH and the silica level were high. The threshold for an aluminum effect, however, was very low (3.5 Î¼g per liter) and did not support the hypothesis of a deleterious effect for only high levels of aluminum. | H17: France | I17: 63 | J17: FALSE | K17: FALSE | L17: FALSE | N17: FALSE | Q17: FALSE | R17: =IF(Q17<>N17,"!!!","") | W17: FALSE
A18: SCOPUS_ID:85102828933 | B18: 10.1016/j.ypmed.2021.106507 | C18: Associations between indicators of energy intake and expenditure with excess weight and obesity among women in sedentary and less-sedentary jobs | D18: Preventive Medicine | E18: 2021 | F18: ['Dietary questionnaire for epidemiological studies', 'Energy balance', 'Obesity', 'Physical activity', 'Saturated fat', 'Sedentary work', 'Sugar sweetened beverages'] | G18: The aim of this study was to compare the associations between indicators of energy intake and expenditure with excess weight and obesity in women who work full-time in sedentary and less sedentary jobs. Data were from 3444 participants the Australian Longitudinal Study on Women's Health, who reported their weight, dietary intake, physical activity and occupation in 2009 (baseline), and weight in 2012 (follow-up). Participants were categorised as being in a â€˜less sedentaryâ€™ or â€˜sedentaryâ€™ job, based on occupational activity patterns. Odds of excess weight (BMI â‰¥ 25) at baseline and of being obese (BMI â‰¥ 30) at follow-up, by indicators of energy intake and expenditure, were compared in the two occupational groups. In multivariate analyses, high non-work sitting time and saturated fat intake were associated with increased odds of obesity at 3-year follow-up in both occupational groups. In the sedentary job group, high physical activity (in leisure and transport) was associated with a 51% reduction in odds of obesity (OR 0.49, 95%CI 0.25â€“0.97). In the less-sedentary job group, energy intake and high soft drink consumption were associated with markedly increased odds of obesity (OR 1.67 95%CI 1.07â€“2.61; OR 2.08 95%CI1.42â€“3.05, respectively). In this cohort of young Australian women, sedentariness at work did not markedly affect the prevalence of excess weight or obesity. Indicators of high energy intake and low energy expenditure were associated with increased odds of both excess weight and obesity, regardless of sedentariness of occupational group. | H18: Australia | I18: 1 | J18: FALSE | K18: FALSE | L18: FALSE | N18: FALSE | Q18: FALSE | R18: =IF(Q18<>N18,"!!!","") | W18: FALSE
A19: SCOPUS_ID:0141997855 | B19: 10.1093/aje/kwg218 | C19: Differences in body shape representations among young adults from a biracial (Black-White), semirural community: The Bogalusa Heart Study | D19: American Journal of Epidemiology | E19: 2003 | F19: ['Blacks', 'Body image', 'Body mass index', 'Body weight', 'Perception', 'Psychology', 'Whites'] | G19: In this study, the authors examined body image perception and body mass index (weight (kg)/height (m)2) among race-gender groups in a biracial (Black-White) population of young adults in Bogalusa, Louisiana. A mail-out survey was completed in 1994 by 3,698 (65%) participants aged 18.5-35 years in the Bogalusa Heart Study (mean age = 27.6 years). As part of the survey, body image perception was determined in terms of body shape representation from a figure rating scale. A body image discrepancy score was calculated from the difference between z-standardized values of body image perception and body mass index. A stepwise proportional odds model including the covariates income, employment, education, and physical activity was used to identify factors influencing lower perception of body shape. Mean body mass index was highest among Black females (p < 0.001). The odds of having a lower perception of body shape (vs. body mass index) were 1.72 times higher in Blacks (p < 0.001), 0.80 times lower in persons who were currently employed (p < 0.001), and 0.86 times lower in persons with a higher education (p = 0.032). Gender, income, and physical activity were not found to be significant predictors of body image perception (p > 0.05). The authors conclude that significant differences exist within racial groups concerning body image perception in relation to overweight status among young adults. This has implications for prevention and education programs. | H19: United States | I19: 84 | J19: FALSE | K19: FALSE | L19: TRUE | M19: "This has implications" - marginal, but still… | N19: TRUE | O19: Hard one, they do say policy implications but without specifying. | P19: LLM prompt edited for generic "this has policy implications" abstracts. New prompt=TRUE | Q19: TRUE | R19: =IF(Q19<>N19,"!!!","") | W19: TRUE
A20: SCOPUS_ID:85195147269 | B20: 10.1007/s10654-024-01134-4 | C20: Trends in incidence and mortality of early-onset cancer in Germany between 1999 and 2019 | D20: European Journal of Epidemiology | E20: 2024 | F20: ['Cancer', 'Germany', 'Incidence', 'Mortality'] | G20: Evidence on the recent temporal trend in the incidence and mortality of early-onset cancer, i.e., cancer diagnosed at ages of < 50 years, in Germany is scarce. To estimate the temporal trend in the incidence and mortality of early-onset cancer in Germany between 1999 and 2019. Input data were obtained from the Centre for Cancer Registry Data (Zentrum fÃ¼r Krebsregisterdaten, ZfKD). The analysis comprised all ages until 50 years and all types of cancer classified by the International Classification of Diseases (ICD-10)-codes C00-C97 (excl. C44). Temporal trends were estimated using negative binomial regression, differentiated by sex and cancer type. Between 1999 and 2019 in Germany, we observed stable or slightly increasing trends (0% and 1%) in the incidence of all early-onset cancers combined (C00-C97) for men and women, respectively, and strict declines in the mortality for both, men and women (-2% and âˆ’ 3%). However, the trends differ largely with respect to sex and the individual cancer types. Early-onset cancer should be closely monitored to see whether stable and decreasing trends in the incidence and mortality continue. Knowing that despite decreasing incidence, the prevalence of a disease can rise due to their interplay with mortality, we recommend to maintain precise surveillance, efforts in prevention and early detection, as well as appropriate investments into healthcare resources, research and development. | H20: Germany | I20: 1 | J20: FALSE | K20: TRUE | L20: TRUE | N20: TRUE | O20: We recommend followed by policy | Q20: TRUE | R20: =IF(Q20<>N20,"!!!","") | W20: TRUE
A21: SCOPUS_ID:0037209068 | B21: 10.1097/00001648-200301000-00009 | C21: The effect of concurvity in generalized additive models linking mortality to ambient particulate matter | D21: Epidemiology | E21: 2003 | F21: ['Air pollution', 'Concurvity', 'Generalized additive model', 'PM 10', 'PM 2.5', 'Sulfate particles'] | G21: In recent years, a number of studies have applied generalized additive models to time series data to estimate associations between exposure to air pollution and cardiorespiratory morbidity and mortality. If concurvity, the nonparametric analogue of multicollinearity, is present in the data, statistical software such as S-plus can seriously underestimate the variance of fitted model parameters, leading to significance tests with inflated type 1 error. This paper uses computer simulation and analyses of actual epidemiologic data to explore this underestimation of standard errors. We provide a method for assessing concurvity in data and an alternate class of models that is unaffected by concurvity. We argue that some degree of concurvity is likely to be present in all epidemiologic time series datasets and we explore through the use of meta-analysis the possible impact of concurvity on the existing body of work relating ambient levels of sulfate particles to mortality. Copyright Â© 2002 by Lippincott Williams & Wilkins, Inc. | H21: Canada | I21: 212 | J21: FALSE | K21: FALSE | L21: FALSE | N21: FALSE | Q21: FALSE | R21: =IF(Q21<>N21,"!!!","") | W21: FALSE
A22: SCOPUS_ID:85097113376 | B22: 10.1093/aje/kwaa139 | C22: Incidence Correction Factors for Moderate and Severe Acute Child Malnutrition from 2 Longitudinal Cohorts in Mali and Burkina Faso | D22: American Journal of Epidemiology | E22: 2020 | F22: ['burden of acute malnutrition', 'child acute malnutrition', 'cumulative incidence', 'incidence correction factor K', 'longitudinal data', 'moderate acute malnutrition', 'prevalence', 'severe acute malnutrition'] | G22: Child acute malnutrition (AM) is an important cause of child mortality. Accurately estimating its burden requires cumulative incidence data from longitudinal studies, which are rarely available in low-income settings. In the absence of such data, the AM burden is approximated using prevalence estimates from cross-sectional surveys and the incidence correction factor $K$, obtained from the few available cohorts that measured AM. We estimated $K$ factors for severe acute malnutrition (SAM) and moderate acute malnutrition (MAM) from AM incidence and prevalence using representative cross-sectional baseline and longitudinal data from 2 cluster-randomized controlled trials (Innovative Approaches for the Prevention of Childhood Malnutrition-PROMIS) conducted between 2014 and 2017 in Burkina Faso and Mali. We compared K estimates using complete (weight-for-length z score, mid-upper arm circumference (MUAC), and edema) and partial (MUAC, edema) definitions of SAM and MAM. $K$ estimates for SAM were 9.4 and 5.7 in Burkina Faso and in Mali, respectively; K estimates for MAM were 4.7 in Burkina Faso and 5.1 in Mali. The MUAC and edema-based definition of AM did not lead to different $K$ estimates. Our results suggest that $K$ can be reliably estimated when only MUAC and edema-based data are available. Additional studies, however, are required to confirm this finding in different settings. | H22: United States | I22: 5 | J22: FALSE | K22: FALSE | L22: FALSE | N22: FALSE | Q22: FALSE | R22: =IF(Q22<>N22,"!!!","") | W22: FALSE
A23: SCOPUS_ID:70249102791 | B23: 10.1093/aje/kwp179 | C23: Determinants of first puff and daily cigarette smoking in adolescents | D23: American Journal of Epidemiology | E23: 2009 | F23: ['Adolescent', 'Epidemiologic factors', 'Incidence', 'Longitudinal studies', 'Risk factors', 'Smoking'] | G23: Few prospective studies of smoking initiation have investigated a wide range of time-varying and invariant predictor variables at the individual and contextual levels concurrently. In this study (1999-2005), 877 Canadian students (mean age=12.7 years) who had never smoked at baseline completed self-report questionnaires on cigarette smoking and 32 predictor variables in 20 survey cycles during secondary school. Height and weight were measured in survey cycles 1, 12, and 19. School administrators completed questionnaires on school tobacco control policies/activities, and trained observers collected data on access to tobacco products in commercial establishments near schools. Younger age, single-parent family status, smoking by parents, siblings, friends, and school staff, stress, impulsivity, lower self-esteem, feeling a need to smoke, not doing well at school, susceptibility to tobacco advertising, alcohol use, use of other tobacco products, and attending a smoking-tolerant school were independent determinants of smoking initiation. Independent determinants of daily smoking onset among initiators of nondaily smoking included smoking by siblings and friends, feeling a need to smoke, susceptibility to tobacco advertising, use of other tobacco products, and self-perceived mental and physical addiction. Adolescent tobacco control programs should address multiple individual and contextual-level risk factors. Strategies that address nicotine dependence symptoms are also needed for adolescents who have already initiated smoking. | H23: Canada | I23: 186 | J23: FALSE | K23: TRUE | L23: TRUE | M23: clear | N23: TRUE | O23: Agreed, with the use of 'strategies' | Q23: TRUE | R23: =IF(Q23<>N23,"!!!","") | W23: TRUE
A24: SCOPUS_ID:0031689886 | B24: 10.1016/S0749-3797(98)00049-X | C24: Costs of maternal conditions attributable to smoking during pregnancy | D24: American Journal of Preventive Medicine | E24: 1998 | F24: ['Cost', 'Economics', 'Health behavior', 'Health care costs', 'Pregnancy', 'Smoking', 'Surveys'] | G24: Context: Despite known adverse health effects, many women continue to smoke during pregnancy. Public attention has now focused on the economic as well as health effects of this behavior. Objective: To estimate health care costs associated with smoking-attributable cases of placenta previa, abruptio placenta, ectopic pregnancy, preterm premature rupture of the membrane (PPROM), pre-eclampsia, and spontaneous abortion. Design: Pooled odds ratios were used with data on total cases to estimate smoking-attributable cases. Estimated average costs for cases of ectopic pregnancy and spontaneous abortion were used to estimate smoking-attributable health care costs for these conditions. Incremental costs, or costs above those for a 'normal' delivery, were used to estimate smoking-attributable costs of placenta previa, abruptio placenta, PPROM, and pre- eclampsia associated with delivery. Setting: National estimates for 1993. Participants: Data from the National Hospital Discharge Survey (NHDS) and claims data from a sample of large, self-insured employers across the country. Results: Smoking- attributable costs ranged from $1.3 million for PPROM to $86 million for ectopic pregnancy. Smoking during pregnancy apparently protects against pre- eclampsia and saves between $36 and $49 million, depending on smoking prevalence. Over all conditions smoking-attributable costs ranged from $135 to $167 million. Conclusions: Smoking during pregnancy is a preventable cause of higher health care costs for the conditions studied. While smoking during pregnancy was found to be protective against pre-eclampsia and, hence, saves costs, the net costs were still positive and significant, Effective smoking- cessation programs can reduce health care costs but clinicians will perhaps need to manage increased cases of pre-eclampsia in a cost-effective manner. | H24: United States | I24: 35 | J24: FALSE | K24: TRUE | L24: TRUE | M24: marginal | N24: TRUE | Q24: TRUE | R24: =IF(Q24<>N24,"!!!","") | W24: TRUE
A25: SCOPUS_ID:85149642428 | B25: 10.2105/AJPH.2022.307207 | C25: Housing Instability and Evictions Linked to Elevated Intimate Partner and Workplace Violence Among Women Sex Workers in Vancouver, Canada: Findings of a Prospective, Community-Based Cohort, 2010-2019 | D25: American Journal of Public Health | E25: 2022 | F25: [] | G25: Objectives. To model the relationship of unstable housing and evictions with physical and sexual violence perpetrated against women sex workers in intimate and workplace settings. Methods. We used bivariate and multivariable logistic regression with generalized estimating equations to model the association of unstable housing exposure and evictions with intimate partner violence (IPV) and workplace violence among a community-based longitudinal cohort of cisgender and transgender women sex workers in Vancouver, Canada, from 2010 through 2019. Results. Of 946 women, 85.9% experienced unstable housing, 11.1% eviction, 26.2% IPV, and 31.8% workplace violence. In multivariable generalized estimating equation models, recent exposure to unstable housing (adjusted odds ratio [AOR]52.04; 95% confidence interval [CI]51.45, 2.87) and evictions (AOR52.45; 95% CI50.99, 6.07) were associated with IPV, and exposure to unstable housing was associated with workplace violence (AOR51.46; 95% CI51.06, 2.00). Conclusions. Women sex workers face a high burden of unstable housing and evictions, which are linked to increased odds of intimate partner and workplace violence. Increased access to safe, womencentered, and nondiscriminatory housing is urgently needed. | H25: United States | I25: 4 | J25: FALSE | K25: TRUE | L25: TRUE | M25: clear | N25: TRUE | Q25: TRUE | R25: =IF(Q25<>N25,"!!!","") | W25: TRUE
A26: SCOPUS_ID:0028286476 | B26: 10.1136/jech.48.3.313 | C26: Estimating confidence limits on a standardised mortality ratio when the expected number is not error free | D26: Journal of Epidemiology & Community Health | E26: 1994 | F26: [] | G26: Objective - The aim was to demonstrate how the beta distribution may be used to find confidence limits on a standardised mortality ratio (SMR) when the expected number of events is subject to random variation and to compare these limits with those obtained with the standard exact approach used for SMRs and with a Fieller-based confidence interval. Design - The relationship of the binomial and the beta distributions is explained. For cohort studies in which deaths are counted in exposed and unexposed groups exact confidence limits on the relative risk are found conditional on the total number of observed deaths. A similar method for the SMR is justified by analogy between the SMR and the relative risk found from such cohort studies, and the fact that the relevant (beta) distribution does not require integer parameters. Source of data - Illustrative examples of hypothetical data were used, together with a MINITAB macro to perform the calculations. Main results - Exact confidence intervals that include error in the expected number are much wider than those found with the standard exact method. Fieller intervals are comparable with the new exact method provided the observed and expected numbers (taken to be means of Poisson variates) are large enough to approximate normality. As the expected number is increased, the standard method gives results closer to the new method, but may still lead to different conclusions even with as many as 100 expected. Conclusions - If there is reason to suppose the expected number of deaths in an SMR is subject to sampling error (because of imprecisely estimated rates in the standard population) then exact confidence limits should be found by the methods described here, or approximate Fieller-based limits provided enough events are observed and expected to approximate normality. | H26: United Kingdom | I26: 40 | J26: FALSE | K26: TRUE | L26: FALSE | M26: clear LLM mistake? | N26: FALSE | O26: Agreed, not sure what it picked up here | P26: me neither - all we can do is a the best with our prompts | Q26: FALSE | R26: =IF(Q26<>N26,"!!!","") | W26: FALSE
A27: SCOPUS_ID:0028784286 | B27: 10.1093/oxfordjournals.aje.a117747 | C27: Preschool physical activity level and change in body fatness in young children: The framingham children's study | D27: American Journal of Epidemiology | E27: 1995 | F27: ['Child', 'Exercise', 'Obesity', 'Prospective studies', 'Skinfold thickness'] | G27: This study examined the effect of preschool physical activity on the change in body fatness from preschool to first grade. The Framingham Children's Study, a longitudinal study of childhood cardiovascular risk behaviors, began in 1987 with the enrollment of 106 children aged 3-5 years and their parents. The present analyses include 97 healthy children with complete data from study entry into first grade. Physical activity was assessed twice yearly for 5 days with an electronic motion sensor. The authors estimated change in the child's level of body fat from preschool to first grade by using the slopes of triceps and subscapular skinfolds and body mass index. On average, active girls (i.e., those with above-median activity levels) gained 1.0 mm in their triceps skinfolds from baseline to first grade, while inactive girls gained 1.75 mm. Active boys lost an average of 0.75 mm in their triceps, while inactive boys gained 0.25 mm. When age, television viewing, energy intake, baseline triceps, and parents' body mass indices were controlled for, inactive preschoolers were 3.8 (95% confidence interval 1.4-10.6) times as likely as active preschoolers to have an increasing triceps slope during follow up (rather than a stable or decreasing slope). This relative risk estimate was slightly higher for children with more body fat at baseline. In this study, preschool-aged children with low levels of physical activity gained substantially more subcutaneous fat than did more active children. Â© 1995 Copyright 1995 by The Johns Hopkins University School of Hygiene and Public Health. | H27: United States | I27: 211 | J27: FALSE | K27: FALSE | L27: FALSE | N27: FALSE | Q27: FALSE | R27: =IF(Q27<>N27,"!!!","") | W27: FALSE
A28: SCOPUS_ID:85123459610 | B28: 10.1093/ije/dyab095 | C28: Maternal smoking and smokeless tobacco use during pregnancy and offspring development: Sibling analysis in an intergenerational Swedish cohort | D28: International Journal of Epidemiology | E28: 2021 | F28: ['confounding', 'fetal growth restriction', 'Intellectual disability', 'maternal prenatal smoking', 'siblings', 'snus'] | G28: Background: The association between maternal smoking in pregnancy and offspring intellectual disability (ID) is less well understood than that of smoking and fetal growth restriction. As fetal growth and cognitive development may share similar confounding structures, comparison of the two associations may improve understanding of the causal nature of the association with ID. Furthermore, comparisons of smoking with smokeless tobacco use may aid identification of mechanisms of action. Methods: This was a cohort study of all Swedish births between 1999 and 2012 (n = 1 070 013), with prospectively recorded data. We assessed the association between maternal smoking during pregnancy and offspring outcomes ID and born small for gestational age (SGA). Analyses were repeated for snus use in pregnancy. Using a sibling design, we estimated within-family effects that control for shared sibling characteristics. Results: Those exposed to maternal smoking in pregnancy had increased odds of ID [odds ratio (OR) = 1.24, 95% confidence interval (CI): 1.16-1.33] and SGA (OR = 2.19, 95% CI: 2.11-2.27) after confounder adjustment. Within-family effects were found for SGA (OR = 1.44, 95% CI: 1.27-1.63) but not ID (OR = 0.92, 95% CI: 0.74-1.14). For snus use, the results for ID were similar to smoking. We found increased odds of offspring SGA among mothers who used snus in pregnancy in sensitivity analyses but not in primary analyses. Conclusions: Our findings are consistent with a causal effect of maternal smoking in pregnancy on risk of offspring born SGA but not on risk of ID. We found no evidence for a causal effect of snus use in pregnancy on ID and inconclusive evidence for SGA. | H28: United Kingdom | I28: 8 | J28: FALSE | K28: FALSE | L28: FALSE | N28: FALSE | Q28: FALSE | R28: =IF(Q28<>N28,"!!!","") | W28: FALSE
A29: SCOPUS_ID:0028997640 | B29: 10.2105/AJPH.85.6.854 | C29: A preventive child health program: The effect of telephone and home visits by public health nurses | D29: American Journal of Public Health | E29: 1995 | F29: [] | G29: A randomized trial was conducted to determine if a public health nursing intervention consisting of telephone contacts or home visits affected the receipt of preventive health services by children eligible for the Early Periodic Screening, Diagnosis, and Treatment program. Each nursing intervention was applied using a protocol, and outcome data for 1654 case subjects were obtained from state-paid provider claims. However, the trial revealed no statistically significant differences between the study groups, nor was ethnicity a significant factor. Methodological and study context issues were identified that may have affected the results, the generalization of which is limited by the strict selection of cases. | H29: United States | I29: 20 | J29: FALSE | K29: FALSE | L29: FALSE | N29: FALSE | Q29: FALSE | R29: =IF(Q29<>N29,"!!!","") | W29: FALSE
A30: SCOPUS_ID:78650909890 | B30: 10.2105/AJPH.2009.182287 | C30: Potential national and state medical care savings from primary disease prevention | D30: American Journal of Public Health | E30: 2011 | F30: [] | G30: Objectives: We estimated national and state-level potential medical care cost savings achievable through modest reductions in the prevalence of several diseases associated with the same lifestyle-related risk factors. Methods: Using Medical Expenditure Panel Survey Household Component data (2003-2005), we estimated the effects on medical spending over time of reductions in the prevalence of diabetes, hypertension, and related conditions amenable to primary prevention by comparing simulated counterfactual morbidity and medical care expenditures to actual disease and expenditure patterns. We produced state-level estimates of spending by using multivariate reweighting techniques. Results. Nationally, we estimated that reducing diabetes and hypertension prevalence by 5% would save approximately $9 billion annually in the near term. With resulting reductions in comorbidities and selected related conditions, savings could rise to approximately $24.7 billion annually in the medium term. Returns were greatest in absolute terms for private payers, but greatest in percentage terms for public payers. State savings varied with demographic makeup and prevailing morbidity. Conclusions. Well-designed interventions that achieve improvements in lifestyle-related risk factors could result in sufficient savings in the short and medium term to substantially offset intervention costs. | H30: United States | I30: 22 | J30: FALSE | K30: TRUE | L30: FALSE | M30: clear LLM mistake? | N30: FALSE | O30: Agreed, not sure what it picked up here | Q30: TRUE | R30: =IF(Q30<>N30,"!!!","") -> !!! | W30: TRUE
A31: SCOPUS_ID:0026733346 | B31: 10.1093/oxfordjournals.aje.a116486 | C31: Childhood weight and growth rate as predictors of adult mortality | D31: American Journal of Epidemiology | E31: 1992 | F31: ['Anthropometry', 'Body height', 'Body weight', 'Child', 'Growth', 'Mortality'] | G31: The effect of rate of growth and relative weight in childhood on adult mortality was studied among 13,146 persons whose weights and heights were measured between the ages of 5 and 18 years in Hagerstown, Maryland, during the period 1933-1945. Relative weight was defined internally, age- and sex-specific Z-scores for height and weight were calculated using national standards, and height and weight velocities were measured as annual increments. Associations between growth parameters (pre- and postpubertal) and mortality through 1985 were investigated in subjects who matched the 1963 and 1975 private health censuses of Washington County, Maryland, using a nested case-control design. Odds ratios of mortality increased linearly with prepubertal relative weight (p < 0.05 for both sexes combined) and with postpubertal relative weight in females (p < 0.01). The associations between growth velocities or attained height with mortality tended to be inverse, although not statistically significant. These results are compatible with the existence of positive associations of overweight in school-age children with long-term mortality and seem to allay fears that harm could come from increased growth rates in childhood. Without jeopardizing growth, the avoidance of overweight in childhood might reduce mortality in middle age. Am J Epidemiol1992;136:201-13. Â© 1992 by The Johns Hopkins University School of Hypiene and Public Health. | H31: United States | I31: 207 | J31: FALSE | K31: TRUE | L31: FALSE | M31: clear LLM mistake? | N31: FALSE | O31: Agreed, not sure what it picked up here | Q31: TRUE | R31: =IF(Q31<>N31,"!!!","") -> !!! | W31: TRUE
A32: SCOPUS_ID:0041509097 | B32: 10.1093/aje/kwg150 | C32: Searching for disease-susceptibility loci by testing for Hardy-Weinberg disequilibrium in a gene bank of affected individuals | D32: American Journal of Epidemiology | E32: 2003 | F32: ['Disease susceptibility', 'Epidemiologic methods', 'Gene library', 'Genetics', 'Genome', 'Hardy-Weinberg equilibrium', 'Monte Carlo method', 'Polymorphism, single nucleotide'] | G32: The future of genetic studies of complex human diseases will rely more and more on the epidemiologic association paradigm. The author proposes to scan the genome for disease-susceptibility gene(s) by testing for deviation from Hardy-Weinberg equilibrium in a gene bank of affected individuals. A power formula is presented, which Is very accurate as revealed by Monte Carlo simulations. If the disease-susceptibility gene is recessive with an allele frequency of â‰¤0.5 or dominant with an allele frequency of â‰¥0.5, the number of subjects needed by the present method is smaller than that needed by using a case-parents design (using either the transmission/disequilibrium test or the 2-df likelihood ratio test). However, the method cannot detect genes with a multiplicative mode of inheritance, and the validity of the method relies on the assumption that the source population from which the cases arise is in Hardy-Weinberg equilibrium. Thus, it is prone to produce false positive and false negative results. Nevertheless, the method enables rapid gene hunting in an existing gene bank of affected individuals with no extra effort beyond simple calculations. | H32: Taiwan | I32: 101 | J32: FALSE | K32: FALSE | L32: FALSE | N32: FALSE | Q32: FALSE | R32: =IF(Q32<>N32,"!!!","") | W32: FALSE
A33: SCOPUS_ID:34247537778 | B33: 10.1093/ije/dyl267 | C33: Are socially disadvantaged neighbourhoods deprived of health-related community resources? | D33: International Journal of Epidemiology | E33: 2007 | F33: ['Community resources', 'Context', 'Health inequality', 'Neighbourhoods', 'New Zealand'] | G33: Background: Recent work in a number of countries has identified growing geographical inequalities in health between deprived and non-deprived neighbourhoods. The health gaps observed cannot be entirely explained by differences in the characteristics of individuals living in those neighbourhoods, which has led to a concerted international public health research effort to determine what contextual features of neighbourhoods matter. This article reports on access to potentially health-promoting community resources across all neighbourhoods in New Zealand. Prevailing international opinion is that access to community resources is worse in deprived neighbourhoods. Methods: Geographical Information Systems were used to calculate geographical access to 16 types of community resources (including recreational amenities, and shopping, educational and health facilities) in 38-350 small census areas across the country. The distribution of these access measures by neighbourhood socioeconomic deprivation was determined. Results: For 15 out of 16 measures of community resources, access was clearly better in more deprived neighbourhoods. For example, the travel time to large supermarkets was âˆ¼80% greater in the least deprived quintile of neighbourhoods compared with the most deprived quintile. Conclusions: These results challenge the widely held, but largely untested, view that areas of high social disadvantage have poorer access to community resources. Poor locational access to community resources among deprived neighbourhoods in New Zealand does not appear to be an explanation of poorer health in these neighbourhoods. If anything, a pro-equity distribution of community resources may be preventing even wider disparities in neighbourhood inequalities in health. Â© The Author 2006; all rights reserved. | H33: New Zealand | I33: 190 | J33: FALSE | K33: FALSE | L33: FALSE | N33: FALSE | Q33: FALSE | R33: =IF(Q33<>N33,"!!!","") | W33: FALSE
A34: SCOPUS_ID:33750628586 | B34: 10.1136/jech.2005.043182 | C34: Validity of age at menarche self-reported in adulthood | D34: Journal of Epidemiology & Community Health | E34: 2006 | F34: [] | G34: Objective: To test the validity of age at menarche self-reported in adulthood and examine whether socioeconomic position, education, experience of gynaecological events and psychological symptoms influence the accuracy of recall. Design: Prospective birth cohort study. Setting: England, Scotland and Wales. Participants: 1050 women from the Medical Research Council National Survey of Health and Development, with two measures of age at menarche, one recorded in adolescence and the other self-reported at age 48 years. Results: By calculating the limits of agreement, Îº statistic and Pearson's correlation coefficients (r), we found that the validity of age at menarche self-reported in middle age compared with that recorded in adolescence was moderate (Îº = 0.35, r = 0.66, n = 1050). Validity was improved by categorising age at menarche into three groups: early, normal and late (Îº = 0.43). Agreement was influenced by educational level and having had a stillbirth or miscarriage. Conclusions: The level of validity shown in this study throws some doubt on whether it is justifiable to use age at menarche self-reported in middle age. It is likely to introduce error and bias, and researchers should be aware of these limitations and use such measures with caution. | H34: United Kingdom | I34: 163 | J34: FALSE | K34: FALSE | L34: FALSE | N34: FALSE | Q34: FALSE | R34: =IF(Q34<>N34,"!!!","") | W34: FALSE
A35: SCOPUS_ID:0344117621 | B35: 10.1093/eurpub/9.3.181 | C35: Physician recommendations for coronary revascularization: Variations by clinical speciality | D35: European Journal of Public Health | E35: 1999 | F35: ['Appropriateness', 'Coronary artery bypass graft surgery', 'Percutaneous transluminal coronary angioplasty'] | G35: Background: Studies have shown that clinical speciality has a strong influence on appropriateness ratings. We examined the effect of clinical speciality on physician recommendations for the performance of coronary artery bypass graft surgery (CABG) and percutaneous transluminal coronary angioplasty (PTCA) in Spain. Methods: Following the RAND appropriateness method, a 10-member multispeciality panel composed of cardiovascular surgeons (CVs), interventional cardiologists (ICs), and non-interventional cardiologists (NICs) rated the appropriateness of 1826 hypothetical indications: 936 for coronary revascularization and 890 for preference between PTCA and CABG. For all revascularization indications and for all PTCA-CABG indications for which revascularization was rated appropriate by the panel, we calculated the mean appropriateness rating, by panellist and by speciality group, and the proportion of indications rated with preference for PTCA, with preference for CABG, and with no preference, by speciality group. Results: The ICs had a higher mean rating across all revascularization indications (7.8) than either the NICs (5.7) or the CVs (5.9). For the 509 indications rated appropriate for revascularization by the panel, the ICs preferred PTCA in 54% of indications, versus 39% for the NICs and 25% for the CVs. The CVs preferred CABG in 58% of indications, versus 32% for the NICs and 20% for the ICs. Conclusions: Appropriateness ratings varied by clinical speciality. Physicians who perform a procedure may be more aggressive in recommending its use than non-performers. Appropriateness panels should be multidisciplinary to accurately reflect the judgements of the different types of physicians involved in patient care. | H35: United States | I35: 16 | J35: FALSE | K35: TRUE | L35: TRUE | M35: hard to call | N35: FALSE | O35: not sure here as it is a practical implication rather than a policy implication. It is hard with the diversity of papers we have. Maybe discuss with our co-authors. | Q35: TRUE | R35: =IF(Q35<>N35,"!!!","") -> !!! | W35: TRUE
A36: SCOPUS_ID:0034541277 | B36: 10.1093/aje/152.11.1072 | C36: Validation of three food frequency questionnaires and 24-hour recalls with serum carotenoid levels in a sample of African-American adults | D36: American Journal of Epidemiology | E36: 2000 | F36: ['Antioxidants', 'Biological markers', 'Carotenoids', 'Diet surveys', 'Fruits', 'Questionnaires', 'Recall', 'Vegetables'] | G36: The validity of self-reported fruit and vegetable intake in minority populations has not been adequately established. In this study, the authors examined the association of three food frequency questionnaires (FFQs) and 24-hour dietary recalls with serum carotenoid levels. Approximately 1,000 African-American adults recruited from 15 churches in Atlanta, Georgia (1997-1998) completed three fruit and vegetable FFQs: a seven-item instrument assessing intake during the past month; a two-item measure assessing usual intake; and a 36-item measure adapted from the Health Habits and History Questionnaire. A total of 414 participants received a 24-hour recall by telephone, and 105 of them received two additional recalls. Serum levels of lycopene, lutein, cryptoxanthin, Î±-carotene, and Î²-carotene were assessed in 813 participants and used as the validity criterion. The correlations of fruit and vegetable servings with specific and total serum carotenoid levels were generally higher for the 36-item FFQ than for the two-item and seven-item instruments. The strongest correlation of fruit and vegetable servings with total carotenoid levels was observed for the three recalls (r = 0.42), with the 36-item FFQ and the single 24-hour recall yielding comparable correlations (r = 0.35 and r = 0.37, respectively). The validity of the 36-item fruit and vegetable FFQ was generally as strong as the validity of both 1 and 3 days of recalls. Given the lower cost and time needed for administration relative to recalls, it appears that the 36-item FFQ has merit for evaluating fruit and vegetable health interventions. | H36: United States | I36: 196 | J36: FALSE | K36: FALSE | L36: FALSE | N36: FALSE | Q36: FALSE | R36: =IF(Q36<>N36,"!!!","") | W36: FALSE
A37: SCOPUS_ID:84885841557 | B37: 10.1016/j.ypmed.2013.07.007 | C37: Who uses new walking and cycling infrastructure and how? Longitudinal results from the UK iConnect study | D37: Preventive Medicine | E37: 2013 | F37: ['Built environment', 'Cycling', 'Infrastructure', 'Walking'] | G37: Objective: To examine how adults use new local walking and cycling routes, and what characteristics predict use. Methods: 1849 adults completed questionnaires in 2010 and 2011, before and after the construction of walking and cycling infrastructure in three UK municipalities. 1510 adults completed questionnaires in 2010 and 2012. The 2010 questionnaire measured baseline characteristics; the follow-up questionnaires captured infrastructure use. Results: 32% of participants reported using the new infrastructure in 2011, and 38% in 2012. Walking for recreation was by far the most common use. In both follow-up waves, use was independently predicted by higher baseline walking and cycling (e.g. 2012 adjusted rate ratio 2.09 (95% CI 1.55, 2.81) for > 450. min/week vs. none). Moreover, there was strong specificity by mode and purpose, e.g. baseline walking for recreation specifically predicted walking for recreation on the infrastructure. Other independent predictors included living near the infrastructure, better general health and higher education or income. Conclusions: The new infrastructure was well-used by local adults, and this was sustained over two years. Thus far, however, the infrastructure may primarily have attracted existing walkers and cyclists, and may have catered more to the socio-economically advantaged. This may limit its impacts on population health and health equity. Â© 2013 The Authors. | H37: Australia | I37: 89 | J37: FALSE | K37: FALSE | L37: FALSE | N37: FALSE | Q37: FALSE | R37: =IF(Q37<>N37,"!!!","") | W37: FALSE
A38: SCOPUS_ID:32344440035 | B38: 10.1016/j.amepre.2005.11.001 | C38: Cigarette promotional offers: Who takes advantage? | D38: American Journal of Preventive Medicine | E38: 2006 | F38: [] | G38: Background: Promotional offers on cigarettes (e.g., dollar-off, multipack discounts) composed the largest share of tobacco industry marketing expenditures, totaling $8.9 billion, or 72% of the total budget in 2002. Internal industry documents indicate that young adults, potential quitters, and other price-sensitive groups are the targets of these marketing tactics. How effective they are in actually reaching these groups in the general population of smokers has not yet been investigated. Methods: Data were from 4618 current smokers responding to the large, random-digit-dialed population-based 2002 California Tobacco Survey. The characteristics were identified of smokers who reported that they used these offers "every time I see one." Results: Thirty-five percent of smokers used promotional offers every time they saw one. Multivariate analyses identified young adults, women, African Americans, those with higher daily cigarette consumption, and those worried about cigarette costs as more likely to use promotional offers at every opportunity. Smokers most committed to quitting were no more likely to use promotional offers than those with no intention to quit. Cigarette brand was highly correlated with age and race/ethnicity, and therefore was not included in the multivariate analysis. Those who smoked menthol cigarettes and Camels, more often young adults and African Americans, were much more likely than those of other brands to use promotional offers. Conclusions: With the exception of smokers intending to quit, cigarette promotional offers are effectively reaching most industry-targeted groups. Importantly, young adults, who have the greatest long-term customer potential, are responding. Â© 2006 American Journal of Preventive Medicine. | H38: United States | I38: 47 | J38: FALSE | K38: FALSE | L38: FALSE | N38: FALSE | Q38: FALSE | R38: =IF(Q38<>N38,"!!!","") | W38: FALSE
A39: SCOPUS_ID:77952942744 | B39: 10.1093/aje/kwq045 | C39: Body fatness at young ages and risk of breast cancer throughout life | D39: American Journal of Epidemiology | E39: 2010 | F39: ['Adiposity', 'Adolescent', 'Breast neoplasms', 'Child', 'Obesity'] | G39: Body fatness at young ages may be related to breast cancer risk independently of adult adiposity. The authors conducted a prospective analysis among 188,860 women (7,582 breast cancer cases) in the Nurses' Health Study (1988-2004) and Nurses' Health Study II (1989-2005) who recalled their body fatness at ages 5, 10, and 20 years using a 9-level pictogram (level 1: most lean; level 9: most overweight). Body fatness at young ages was inversely associated with risk of both premenopausal and postmenopausal breast cancer (per 1-unit increase in adolescent body fatness, relative risk (RR) = 0.88 and RR = 0.91, respectively; Ptrend < 0.0001). Among all women, the RR for adolescent body fatness of level 6.5 or higher versus level 1 was 0.57 (per 1-unit increase, RR = 0.90; Ptrend < 0.0001) and was unaffected by adjustment for current body mass index. The association was stronger for women with birth weights under 8.5 pounds (<3.9 kg) than for women with birth weights of 8.5 pounds or more (â‰¥3.9 kg) (per 1-unit increase, RR = 0.89 and RR = 0.94, respectively; Pinteraction = 0.04) and stronger for estrogen receptor-negative tumors than for estrogen receptor-positive tumors (per 1-unit increase, RR = 0.86 and RR = 0.92, respectively; Pheterogeneity = 0.03). Body fatness at young ages has a strong and independent inverse relation to breast cancer risk throughout life. Â© The Author 2010. | H39: United States | I39: 187 | J39: FALSE | K39: FALSE | L39: FALSE | N39: FALSE | Q39: FALSE | R39: =IF(Q39<>N39,"!!!","") | W39: FALSE
A40: SCOPUS_ID:85133308008 | B40: 10.1016/j.ypmed.2022.107128 | C40: Correlates of behavior change intents in response to a hypothetical flavored cigar sales restriction among U.S. adult flavored cigar smokers | D40: Preventive Medicine | E40: 2022 | F40: ['Cigar prevention', 'Cigarillos', 'Cigars', 'Flavored tobacco', 'Health disparities', 'Large cigars', 'Tobacco policy'] | G40: Flavored cigar sales restrictions (FCSRs) may reduce cigar smoking and protect public health. This study examined the correlates of behavior change intents in response to a hypothetical FCSR. Data were from a nationally representative sample of adult flavored cigar smokers (ages â‰¥21; n = 343) collected through an online survey in 2021. Respondents selected their behavior change intents in response to a hypothetical FCSR, including (1) quitting cigars altogether; (2) smoking plain or non-flavored cigars; (3) smoking other flavored tobacco products; (4) smoking cannabis; and (5) other options. Weighted logistic regressions were used to examine the associations of socio-demographic backgrounds, tobacco use history, and tobacco dependence with behavioral change intents. In response to an FCSR, 15.1% of respondents would quit smoking cigars altogether, 41.6% would smoke plain cigars without flavors, 33.4% would substitute flavored cigars with other flavored tobacco products, and 29.2% would substitute flavored cigars with cannabis. Large cigar smokers and blunt smokers were less likely to quit cigars altogether than non-smokers of those products; females and racial/ethnic minorities were more likely to substitute flavored cigars with other flavored tobacco and cannabis products, respectively, than males and non-Hispanic White respondents. Results suggest that FCSRs may reduce cigar smoking among a portion of U.S. flavored cigar smokers while leaving more continuing to smoke plain cigars or transitioning to use other flavored tobacco products or cannabis. Implementing FCSRs should be accompanied by comprehensive flavored tobacco sales restrictions, cessation programs, and educational messages aimed at reducing the use of cigars and other substances. | H40: United States | I40: 5 | J40: FALSE | K40: TRUE | L40: TRUE | M40: clear | N40: TRUE | O40: Agreed, with the use of 'should' followed by clear policy implications. | Q40: TRUE | R40: =IF(Q40<>N40,"!!!","") | W40: TRUE
A41: SCOPUS_ID:84929335072 | B41: 10.2105/AJPH.2015.302628 | C41: Polling places, pharmacies, and public health: Vote &amp; Vax 2012 | D41: American Journal of Public Health | E41: 2015 | F41: [] | G41: US national elections, which draw sizable numbers of older voters, take place during flu-shot season and represent an untapped opportunity for large-scale delivery of vaccinations. In 2012, Vote & Vax deployed a total of 1585 clinics in 48 states; Washington, DC; Guam; Puerto Rico; and the US Virgin Islands. Approximately 934 clinics were located in pharmacies, and 651 were near polling places. Polling place clinics delivered significantly more vaccines than did pharmacies (5710 vs 3669). The delivery of vaccines was estimated at 9379, and approximately 45% of the recipients identified their race/ethnicity as African American or Hispanic. More than half of the White Vote & Vax recipients and more than two thirds of the non-White recipients were not regular flu shot recipients. | H41: United States | I41: 3 | J41: FALSE | K41: FALSE | L41: FALSE | N41: FALSE | Q41: FALSE | R41: =IF(Q41<>N41,"!!!","") | W41: FALSE
A42: SCOPUS_ID:85133980653 | B42: 10.1093/aje/kwac025 | C42: Sampling Validation Data to Achieve a Planned Precision of the Bias-Adjusted Estimate of Effect | D42: American Journal of Epidemiology | E42: 2022 | F42: ['epidemiologic methods', 'quantitative bias analysis', 'study design', 'validation substudies'] | G42: Data collected from a validation substudy permit calculation of a bias-adjusted estimate of effect that is expected to equal the estimate that would have been observed had the gold standard measurement been available for the entire study population. In this paper, we develop and apply a framework for adaptive validation to determine when sufficient validation data have been collected to yield a bias-adjusted effect estimate with a prespecified level of precision. Prespecified levels of precision are decided a priori by the investigator, based on the precision of the conventional estimate and allowing for wider confidence intervals that would still be substantively meaningful. We further present an applied example of the use of this method to address exposure misclassification in a study of transmasculine/transfeminine youth and self-harm. Our method provides a novel approach to effective and efficient estimation of classification parameters as validation data accrue, with emphasis on the precision of the bias-adjusted estimate. This method can be applied within the context of any parent epidemiologic study design in which validation data will be collected and modified to meet alternative criteria given specific study or validation study objectives. | H42: United States | I42: 1 | J42: FALSE | K42: FALSE | L42: FALSE | N42: FALSE | Q42: FALSE | R42: =IF(Q42<>N42,"!!!","") | W42: FALSE
A43: SCOPUS_ID:0028170572 | B43: 10.2105/AJPH.84.9.1439 | C43: Black-White differences in serum cotinine levels among pregnant women and subsequent effects on infant birthweight | D43: American Journal of Public Health | E43: 1994 | F43: [] | G43: Objectives. Higher levels of serum cotinine (a metabolite of nicotine) have been found in Black smokers than in White smokers even after self- reported cigarette dose was controlled. It is unknown whether higher cotinine levels in Black pregnant smokers may increase the risk of delivering an infant of reduced birthweight. Methods. We analyzed serum cotinine levels of 374 Black and 829 White women who smoked during pregnancy and who delivered between April 1964 and April 1967. Racial differences in the relationship between cotinine and birthweight were examined. Results. Cotinine levels were 27.4 ng/mL higher in Black smokers after cigarette dose and confounding variables were controlled. Blacks had higher cotinine levels than Whites at each dose. No significant racial differences in the rate of decrease in birthweight per nanogram of cotinine per milliliter were found. Conclusions. Our results confirm previous research showing higher cotinine levels at each smoking dose in Black smokers than in White smokers. Because there was no difference in the rate of decrease in birthweight due to cotinine, our results suggest that cigarette smoking among Blacks may have a greater effect on birthweight than it does among Whites. | H43: United States | I43: 95 | J43: FALSE | K43: FALSE | L43: FALSE | N43: FALSE | Q43: FALSE | R43: =IF(Q43<>N43,"!!!","") | W43: FALSE
A44: SCOPUS_ID:79952050640 | B44: 10.1093/ije/dyq164 | C44: Prospective cohort study of breast implants and the risk of connective-tissue diseases | D44: International Journal of Epidemiology | E44: 2011 | F44: ['Breast implants', 'Cohort studies', 'Connective-tissue diseases', "Women's health"] | G44: Background: A 2000 meta-analysis indicated no overall association between breast implants and risk of connective-tissue diseases (CTDs). However, a large retrospective cohort study we previously conducted suggested, instead, a small increased risk of CTDs. Because of limitations inherent to the retrospective cohort study design, we sought clarification by conducting a prospective cohort study of the association of breast implants with CTD risk. Methods:: Participants were 23 847 US women (mean age 56.6 years), 3950 of whom had breast implants and 19 897 did not. Women reported their breast implant status at baseline in 2001 and were followed for a median of 3.63 years. During follow-up, women reported incident CTD, confirmed using a CTD screening questionnaire (CSQ) and medical records. Results: In multivariate analyses, the rate ratios for self-reported CTD (113 vs 377 cases in the implanted and non-implanted group, respectively) were 1.60 [95% confidence interval (CI) 1.28-2.00], for CSQ-confirmed CTD (77 vs 226 cases), 1.80 (1.37-2.38) and for medical ecord confirmed CTD (21 vs 74 cases), 1.39 (0.82-2.35). Conclusions: Although this prospective cohort study represented a stronger design than the retrospective cohort study, the present data should still be viewed cautiously because of remaining methodological limitations, including the potential for differential self-reporting of CTD and CTD symptoms among women with and without breast implants, the difficulty of obtaining medical records for women reporting CTD and the low and possibly differential confirmation of self-reported disease against medical records. A reasonable conclusion is the lack of a large increase in CTD risk (e.g.â‰¥2-fold) associated with breast implants. Â© The Author 2010. Published by Oxford University Press on behalf of the International Epidemiological Association. All rights reserved. | H44: United States | I44: 20 | J44: FALSE | K44: FALSE | L44: FALSE | N44: FALSE | Q44: FALSE | R44: =IF(Q44<>N44,"!!!","") | W44: FALSE
A45: SCOPUS_ID:0041803240 | B45: 10.1023/A:1024686625528 | C45: Birth weight and risk of angina pectoris: Analysis in Swedish twins | D45: European Journal of Epidemiology | E45: 2003 | F45: ['Angina pectoris', 'Birth weight', 'Coronary heart disease', 'Twin study'] | G45: Objective: Intrauterine nutrition approximated by birth weight has been shown to be inversely associated with risk of coronary heart disease (CHD). By investigating the association within twin pairs discordant for disease, the influence of genetic and early environmental factors is substantially reduced. Methods: We have investigated the association between birth weight and angina pectoris in same-sexed twins with known zygosity included in the population-based Swedish Twin Registry. Self-reports of birth weight and angina pectoris were collected in a telephone interview between 1998 and 2000. The cohort analyses were based on 4594 same-sexed twins, and the within-pair analyses included 55 dizygotic and 37 monozygotic twin pairs discordant for angina pectoris. Odds ratios (OR) and 95% confidence intervals (CI) were calculated by logistic regression. Results: Compared with birth weight between 2.0 and 2.9 kg, low birth weight (<2.0 kg) was associated with increased risk of angina pectoris in the twin cohort, (OR: 1.46; 95% CI: 1.14-1.87), but after adjustment for potential confounders the risk decreased, and did not reach significance. Within twin pairs discordant for angina pectoris, low birth weight was significantly associated with increased risk of angina pectoris within dizygotic twins (adjusted OR: 5.73; 95% CI: 1.59-20.67), but not within monozygotic twins (adjusted OR: 1.20; 95% CI: 0.40-3.58). Conclusions: The results suggest that genetic differences associated with foetal growth and adult risk of CHD may have affected previously reported associations between birth weight and CHD. | H45: Sweden | I45: 17 | J45: FALSE | K45: FALSE | L45: FALSE | N45: FALSE | Q45: FALSE | R45: =IF(Q45<>N45,"!!!","") | W45: FALSE
A46: SCOPUS_ID:16544383725 | B46: 10.1023/B:EJEP.0000036814.56108.66 | C46: Estimating non-response bias in family studies: Application to mental health and lifestyle | D46: European Journal of Epidemiology | E46: 2004 | F46: ['Health and lifestyle', 'Mailed survey', 'Mental state', 'Non-response', 'Personality', 'Twin-family design'] | G46: Non-response to mailed surveys reduces the effective sample size and may introduce bias. Non-response has been studied by (1) comparison to available data in population based registers, (2) directly contacting non-respondents by telephone or single-item reply cards, and (3) longitudinal repetition of the survey. The goal of this paper was to propose an additional method to study non-response bias: when the variable of interest has a familial component, data from respondents can be used as proxy for the data from their non-responding family members. This approach was used with data on smoking, alcohol consumption, physical activity, coffee- and tea-use, education, body mass index, religion, burnout, life events, personality and mental health in large number of siblings and DZ twins registered with the Netherlands Twin Register. In addition, for smoking behavior, we also used the second strategy by sending a reply card. Results show that scores of members from less cooperative families or incomplete twin pairs tended to be more unfavorable than the scores from highly cooperative families or complete twin pairs. For example, family members from less cooperative families cycled less often and scored higher on anxious depression and neuroticism. For smoking, both the results of the reply card and the results of the additional method suggested a higher percentage smokers among the non-respondents but this was only significant with reply card method. In general, differences between highly/less cooperative families and complete/incomplete DZ twins were small. Results suggest that, even for studies with moderate response rates, data collected on health, personality and lifestyle are relatively unbiased. Â© 2004 Kluwer Academic Publishers. | H46: Netherlands | I46: 80 | J46: FALSE | K46: FALSE | L46: FALSE | N46: FALSE | Q46: FALSE | R46: =IF(Q46<>N46,"!!!","") | W46: FALSE
A47: SCOPUS_ID:0030889263 | C47: The Dutch EPIC Food Frequency Questionnaire. I. Description of the questionnaire, and relative validity and reproducibility for food groups | D47: International Journal of Epidemiology | E47: 1997 | F47: ['EPIC', 'Food frequency questionnaire', 'Food groups', 'Food photographs', 'Relative validity', 'Reproducibility'] | G47: Background. A self-administered food frequency questionnaire was developed for the Dutch cohort of the European Prospective Investigation into Cancer and Nutrition (EPIC). Habitual consumption of 178 food items can be calculated from the questionnaire data. Methods. Reproducibility and relative validity for food group intake were investigated in a population of 121 Dutch men and women. The questionnaire was administered three times at 6-month intervals in order to determine the reproducibility. To assess the relative validity 12 monthly 24-hour recalls served as the reference method. Results. Spearman rank order correlation coefficients between estimates of food group intake assessed by repeated questionnaires ranged from 0.45 to 0.92. For men, Spearman correlation coefficients between estimates of food group intake based on the questionnaire and those based on 24-hour recalls ranged from 0.21 for cooked vegetables to 0.78 for sugar and sweet products, with a range of 0.61. For women the median was 0.53, with a minimum of 0.31 for vegetables and a maximum of 0.87 for alcoholic beverages. The photographs in the questionnaire for the estimation of portion sizes contributed little to the relative validity of the ranking of subjects. However, on the group level most median food group estimates based on photographic portion sizes were closer to the median intakes as assessed by 24-hour recalls than those based on standard portion sizes. Conclusions. The questionnaire seems adequate for ranking Dutch EPIC subjects according to intake of most food groups, although the relative validity for some food groups, such as vegetables and fish, remains of concern. | H47: Netherlands | I47: 362 | J47: FALSE | K47: FALSE | L47: FALSE | N47: FALSE | Q47: FALSE | R47: =IF(Q47<>N47,"!!!","") | W47: FALSE
A48: SCOPUS_ID:85022341794 | B48: 10.1016/j.ypmed.2017.07.005 | C48: Is the link between movement and mental health a two-way street? Prospective associations between physical activity, sedentary behaviour and depressive symptoms among women living in socioeconomically disadvantaged neighbourhoods | D48: Preventive Medicine | E48: 2017 | F48: ['Exercise, sedentary lifestyle', 'Mental health', 'Sitting', 'Vulnerable populations', 'Women'] | G48: This study aimed to investigate the bi-directional relationship between different domains of physical activity (PA), sedentary behaviour (SB) and depressive symptoms among women living in socioeconomically disadvantaged neighbourhoods in Victoria, Australia. Women (nÂ =Â 1033), aged 18â€“46Â years at Wave 1 (2007/08), completed self-report measures of PA (leisure-time, transport, occupational, domestic), SB (TV viewing, computer use, overall sitting time) and depressive symptoms (CES-D 10) at each study time-point (Wave 2: 2010/11, Wave 3: 2012/13). Separate linear mixed models were fitted to examine if change in depressive symptoms differed dependent on each of the baseline PA or SB measures. Similarly, baseline depressive symptoms were used as a predictor of change in PA and SB. In secondary analyses, associations between baseline PA or SB and odds of becoming â€˜at riskâ€™ of depression among those not â€˜at riskâ€™ at baseline were examined using logistic regression. There was no evidence that change in depressive symptoms differed depending on PA or SB at baseline. In general, there was also no evidence that change in PA or SB differed depending on baseline depressive symptoms. One exception was change in leisure-time PA, which declined more among those with heightened depressive symptoms at baseline (Interaction: Î²Â =Â âˆ’Â 0.003, 95% CIÂ =Â âˆ’Â 0.007, âˆ’Â 0.0003). Transport-related PA (adjusted ORÂ =Â 1.06, 95% CIÂ =Â 1.013, 1.101) and domestic PA (adjusted ORÂ =Â 1.02, 95% CIÂ =Â 1.003, 1.040) were associated with greater odds of becoming at risk of depression at wave 3. There was limited evidence of a bi-directional relationship between PA, SB and depressive symptoms in women living in socioeconomically disadvantaged neighbourhoods. | H48: Australia | I48: 27 | J48: FALSE | K48: FALSE | L48: FALSE | N48: FALSE | Q48: FALSE | R48: =IF(Q48<>N48,"!!!","") | W48: FALSE
A49: SCOPUS_ID:0029949732 | B49: 10.1006/pmed.1996.0058 | C49: Exposure to environmental tobacco smoke - Perceptions of African American children and adolescents | D49: Preventive Medicine | E49: 1996 | F49: ['attitudes', 'environmental tobacco smoke', 'knowledge', 'preventive efforts'] | G49: Background. A study was designed to investigate the knowledge, attitudes, and preventive efforts with regard to exposure to environmental tobacco smoke (ETS) among a sample of urban African American children and adolescents. Methods. A sample of 675 students enrolled in grades 5 through 12 in an urban public school district located in the greater metropolitan area of Detroit, Michigan, was surveyed. Results. Smoking rates among students were higher if someone else in the home was a smoker and lower if there were no other smokers in the home. Forty-eight percent of the students reported that their fathers smoked, while 46% reported mothers who smoked. In each of the areas knowledge, attitudes, and preventive efforts, elementary students scored highest and middle school students scored lowest. Attitude scores were higher if the mother or father was a nonsmoker, and nonsmokers scored higher than smokers on knowledge, attitudes, and preventive efforts. Students' preventive efforts were significantly predicted by their knowledge, attitudes, and gender, while their attitudes were in turn predicted by their knowledge, gender, school level, and smoking status and by the proportion of their friends who were smokers. Students' knowledge was significantly predicted by their gender and school level and by the proportion of their siblings who were smokers. Conclusions. It is apparent that many of the African American students surveyed in this study experience significant exposure to ETS, particularly in the home. As is evident from the literature, this has implications for the long term health of these youngsters. Health education and promotion efforts should be directed not only toward the students themselves, but should also address the smoking behavior of parents and others in the home environment. | H49: United States | I49: 20 | J49: FALSE | K49: TRUE | L49: TRUE | M49: clear | N49: TRUE | O49: Agreed, clear policy recommendation, with use of 'should' | Q49: TRUE | R49: =IF(Q49<>N49,"!!!","") | W49: TRUE
A50: SCOPUS_ID:85054071416 | B50: 10.1097/EDE.0000000000000857 | C50: Performance of between-study heterogeneity measures in the cochrane library | D50: Epidemiology | E50: 2018 | F50: ['Cochrane Library', 'Heterogeneity', 'I statistic 2', 'Meta-analysis', 'Outlying studies'] | G50: The growth in comparative effectiveness research and evidence-based medicine has increased attention to systematic reviews and meta-analyses. Meta-analysis synthesizes and contrasts evidence from multiple independent studies to improve statistical efficiency and reduce bias. Assessing heterogeneity is critical for performing a meta-analysis and interpreting results. As a widely used heterogeneity measure, the I2 statistic quantifies the proportion of total variation across studies that is caused by real differences in effect size. The presence of outlying studies can seriously exaggerate the I2 statistic. Two alternative heterogeneity measures, the Ir2 and Im2 , have been recently proposed to reduce the impact of outlying studies. To evaluate these measures' performance empirically, we applied them to 20,599 meta-analyses in the Cochrane Library. We found that the Ir2 and Im2 have strong agreement with the I2, while they are more robust than the I2 when outlying studies appear. | H50: China | I50: 28 | J50: FALSE | K50: FALSE | L50: FALSE | N50: FALSE | Q50: FALSE | R50: =IF(Q50<>N50,"!!!","") | W50: FALSE
A51: SCOPUS_ID:85085015109 | B51: 10.1016/j.amepre.2020.03.024 | C51: Alcohol Use and Suicidality by Sexual Orientation Among U.S. Youth, 2009â€“2017 | D51: American Journal of Preventive Medicine | E51: 2020 | F51: [] | G51: Introduction: Alcohol use and suicidality remain serious risks for U.S. youth. Research has established that disparities exist in these outcomes between heterosexual and sexual minority youth. However, research into the associations between alcohol use and suicidality has yet to consider the differential role of sexual orientation. Methods: Using a pooled, diverse sample from the 2009â€“2017 Youth Risk Behavior Survey, associations of alcohol use and suicidality by sex and sexual orientation, and changes in these outcomes over time, were investigated. Analyses were conducted in 2019. Results: Suicidality was highest among nonheterosexuals, who ranged from twofold to sevenfold higher odds to report suicidality across all time points, with the most striking disparities among male sexual minority youth. Rates among all students remained stable or increased over time; notable exceptions included a decrease in suicide attempts among bisexual students. Among all students, current alcohol use was associated with elevated levels of suicidality. For female students, the association between drinking and suicidality did not significantly differ by sexual identity; for male students, it was significant regardless of sexual identity and most pronounced among not sure youth. Conclusions: These results emphasize the need for additional research into the relationship between contemporaneous alcohol use and suicidality, with attention to differences based on sex, sexual orientation, and other factors that may impact these relationships. There is a particular need for research to examine the temporal nature of the association such that evidence-informed, high-impact interventions can be developed to improve suicidality outcomes among sexual minority youth. | H51: United States | I51: 8 | J51: FALSE | K51: FALSE | L51: FALSE | N51: FALSE | Q51: FALSE | R51: =IF(Q51<>N51,"!!!","") | W51: FALSE
A52: SCOPUS_ID:0033962566 | B52: 10.1006/pmed.1999.0608 | C52: Changes in serum total cholesterol levels over 18 years in a cohort of men and women: The Nijmegen cohort study | D52: Preventive Medicine | E52: 2000 | F52: ['Cholesterol', 'Cohort', 'Epidemiology'] | G52: Background. This study aimed to investigate to what extent cholesterol levels change in individuals in different age groups over an 18-year period. Factors that contribute to the changes, with respect to prevention of cardiovascular disease, were taken into account. Methods. In 1977 serum cholesterol, systolic and diastolic blood pressures, body mass index, and smoking habits were measured in a cohort of 7,092 patients (men and women from 20 to 50 years of age) from six general practices in The Netherlands. In 1995, a sample of 2,600 of these same patients were invited to take part in a similar screening program; 2,335 patients, consisting of 1,171 men and 1,164 women, agreed to participate. Patients were derived from both high-risk and low- to normal-risk category in 1977. The differences in cholesterol between 1977 and 1995 were calculated and cholesterol levels were tracked over the study period by determining Pearson correlation coefficients. A multiple linear regression analysis was performed to investigate the determinants influencing the changes in cholesterol level. Results. The mean cholesterol levels rose during the study period in all age groups. The highest mean increase in men was 1.23 mmol/L, or 20%, in the youngest age group (20-24 years), and in women the maximum mean increase was 1.12 mmol/L, or 17%, in the age group 40-44 years. Correlation coefficients between the 1977 and 1995 readings varied from 0.63 in the youngest age group to 0.41 in the oldest. Body weight change during the study period, more than initial body weight, was found to have influenced the rise in serum cholesterol. At basic screening, 19.2% of the men and 12.4% of the women had cholesterol levels of 6.5 mmol/L or higher, as against 35.8 and 36.8%, respectively, in 1995. Conclusions. Over an 18-year period cholesterol level increased in most subjects, at a younger age in men than in women. The highest increase in women took place during the menopausal period. Weight gain, more than baseline weight, had a positive influence on the increase in cholesterol. (C) 2000 American Health Foundation and Academic Press. | H52: Netherlands | I52: 16 | J52: FALSE | K52: FALSE | L52: FALSE | N52: FALSE | Q52: FALSE | R52: =IF(Q52<>N52,"!!!","") | W52: FALSE
A53: SCOPUS_ID:84959905141 | B53: 10.1016/j.ypmed.2016.02.001 | C53: The influence of electronic cigarette age purchasing restrictions on adolescent tobacco and marijuana use | D53: Preventive Medicine | E53: 2016 | F53: ['E-cigarettes', 'Electronic nicotine delivery systems', 'Minimum legal purchase age', 'Tobacco control'] | G53: Objective In the United States, many states have established minimum legal purchase ages for electronic nicotine delivery systems (ENDS) to ban adolescent purchases, but these policies may also affect other related substance use. We explore whether ENDS are substitutes or complements for cigarettes, cigars, smokeless tobacco, and marijuana among adolescents by using variation in state-level implementation of ENDS age purchasing restrictions. Methods We linked data on ENDS age purchasing restrictions to state- and year-specific rates of adolescent tobacco and marijuana use in 2007â€“2013 from the Youth Risk Behavior Surveillance System. This data provides a nationally representative sample of adolescents who attend public and private schools. We performed a fixed effect regression analysis exploring the influence of ENDS age purchasing restrictions on outcomes of tobacco use and marijuana use, controlling for state and year fixed characteristics, age-race cohorts, cigarette excise taxes, and cigarette indoor use restrictions. Results For cigarette use, we separate our results into cigarette use frequency. We found causal evidence that ENDS age purchasing restrictions increased adolescent regular cigarette use by 0.8 percentage points. ENDS age purchasing restrictions were not associated with cigar use, smokeless tobacco use, or marijuana use. Conclusions We document a concerning trend of cigarette smoking among adolescents increasing when ENDS become more difficult to purchase. | H53: United States | I53: 72 | J53: FALSE | K53: FALSE | L53: FALSE | N53: FALSE | Q53: FALSE | R53: =IF(Q53<>N53,"!!!","") | W53: FALSE
A54: SCOPUS_ID:84890514902 | B54: 10.1093/eurpub/cks187 | C54: Association between parental perceptions of residential neighbourhood environments and childhood obesity in Porto, Portugal | D54: European Journal of Public Health | E54: 2013 | F54: [] | G54: Background: Portugal has one of the highest rates of childhood obesity in Europe. Few studies have explored the relationship between parents' perceptions of their residential neighbourhood (safety concerns and amenities of the built environment) and their children's weight status. This study aims to examine the associations between parents' perceptions of their residential neighbourhood and overweight/obesity among their children. Methods: Anthropometric measures of height and weight were taken for 2690 children in preschools and elementary schools in Porto. Body mass index (kg/m2) was calculated, and the International Obesity Taskforce (IOTF) cut-offs were used. Parents completed the 'Environmental Module' standard questionnaire of the International Physical Activity Prevalence Study. Chi-square tests and the logistic regression model adjusted for age, gender, maternal education and school cluster were used to examine the associations between parents' perceptions of their residential neighbourhood and overweight/obesity among their children. Results: In this sample, 31.8% of the children were overweight (including obese). Significant associations were found between child obesity and the following residential environmental characteristics: the odds of children being obese were lower if their parents believed that it was safe (low/no crime rate) to walk/cycle at night (OR = 0.65, 95% CI = 0.54-0.79) and during the day (OR = 0.70, 95% CI = 0.55-0.86) and that it was easy and pleasant (pedestrian safety) to walk in their neighbourhoods (OR = 0.73, 95% CI = 0.58-0.90) and when local sidewalks were well maintained and unobstructed (OR = 1.18, 95% CI = 1.01-1.40). Conclusion: Parental perceptions of neighbourhood safety and the quality of local sidewalks are significantly associated with obesity values. Â© 2013 The Author. | H54: Portugal | I54: 13 | J54: FALSE | K54: FALSE | L54: FALSE | N54: FALSE | Q54: FALSE | R54: =IF(Q54<>N54,"!!!","") | W54: FALSE
A55: SCOPUS_ID:67749091014 | B55: 10.1093/aje/kwp143 | C55: Age of onset in concordant twins and other relative pairs with multiple sclerosis | D55: American Journal of Epidemiology | E55: 2009 | F55: ['Age of onset', 'Environment', 'Family', 'Genetics', 'Multiple sclerosis', 'Twins'] | G55: The ages of onset in multiple sclerosis cases span more than 7 decades. Data are presented for affected relative pairs from a Canadian population base of 30,000 multiple sclerosis index cases (1993-2008). The effects of genetic sharing, parent of origin, intergenerational versus collinear differences, and gender on the ages of onset were evaluated in the following concordant pairs: monozygotic twins (n=29), dizygotic twins (n=10), siblings (n=614), first cousins (n=405), half siblings (n=29), parent/child (n=285), and aunt/uncle/niece/nephew (avunculars) (n=289). Fisher's z test assessed intraclass correlation (r) for ages of onset. Correlations for monozygotic twins, dizygotic twins, full siblings, and first cousins were 0.60, 0.54, 0.20, and 0.10, respectively. Dizygotic twins resembled monozygotic twins more than siblings. The age-of-onset correlation for maternal half siblings (r=0.37) was higher than that for paternal half siblings (r=0.26), consistent with other observations suggesting an intrauterine environmental effect on multiple sclerosis risk. Intergenerational comparisons are complicated by substantial increases of multiple sclerosis incidence over time. Genetic loading (familial vs. sporadic cases) did not generally influence the age of onset, but correlation of age of onset in multiple sclerosis relative pairs was proportional to genetic sharing. A maternal parent-of-origin effect on the age of onset in collinear generations was suggested. Â© 2009 The Authors. | H55: Canada | I55: 27 | J55: FALSE | K55: FALSE | L55: FALSE | N55: FALSE | Q55: FALSE | R55: =IF(Q55<>N55,"!!!","") | W55: FALSE
A56: SCOPUS_ID:84877257399 | B56: 10.1093/aje/kws330 | C56: Association of functional polymorphism rs2231142 (Q141K) in the ABCG2 gene with serum uric acid and gout in 4 US populations | D56: American Journal of Epidemiology | E56: 2013 | F56: ['ABCG2 protein, human', 'genetic association studies', 'gout', 'meta-analysis', 'polymorphism, single nucleotide', 'urate transporter', 'uric acid'] | G56: A loss-of-function mutation (Q141K, rs2231142) in the ATP-binding cassette, subfamily G, member 2 gene (ABCG2) has been shown to be associated with serum uric acid levels and gout in Asians, Europeans, and European and African Americans; however, less is known about these associations in other populations. Rs2231142 was genotyped in 22,734 European Americans, 9,720 African Americans, 3,849 Mexican Americans, and 3,550 American Indians in the Population Architecture using Genomics and Epidemiology (PAGE) Study (2008-2012). Rs2231142 was significantly associated with serum uric acid levels (P = 2.37 Ã— 10-67, P = 3.98 Ã— 10-5, P = 6.97 Ã— 10 -9, and P = 5.33 Ã— 10-4 in European Americans, African Americans, Mexican Americans, and American Indians, respectively) and gout (P = 2.83 Ã— 10-10, P = 0.01, and P = 0.01 in European Americans, African Americans, and Mexican Americans, respectively). Overall, the T allele was associated with a 0.24-mg/dL increase in serum uric acid level (P = 1.37 Ã— 10-80) and a 1.75-fold increase in the odds of gout (P = 1.09 Ã— 10-12). The association between rs2231142 and serum uric acid was significantly stronger in men, postmenopausal women, and hormone therapy users compared with their counterparts. The association with gout was also significantly stronger in men than in women. These results highlight a possible role of sex hormones in the regulation of ABCG2 urate transporter and its potential implications for the prevention, diagnosis, and treatment of hyperuricemia and gout. Â© 2013 The Author. | H56: United States | I56: 71 | J56: FALSE | K56: FALSE | L56: FALSE | M56: I think it's not a policy recommendation. Studies making strong causal claims != policy claims. An interesting but different RQ I think | N56: FALSE | O56: This one made me think of our sample selection - on this topic they will obviously not make a policy recommendation but is it still ok to make a strong causal statement? | Q56: FALSE | R56: =IF(Q56<>N56,"!!!","") | W56: FALSE
A57: SCOPUS_ID:84857279547 | B57: 10.2105/AJPH.2011.300295 | C57: Position-specific HIV risk in a large network of homeless youths | D57: American Journal of Public Health | E57: 2012 | F57: [] | G57: We examined interconnections among runaway and homeless youths (RHYs) and how aggregated network structure position was associated with HIV risk in this population. Methods. We collected individual and social network data from 136 RHYs.On the basis of these data, we generated a sociomatrix, accomplished network visualization with a "spring embedder," and examined k-cores. We used multivariate logistic regression models to assess associations between peripheral and nonperipheral network position and recent unprotected sexual intercourse. Results. Small numbers of nominations at the individual level aggregated into a large social network with a visible core, periphery, and small clusters. Female youths were more likely to be in the core, as were youths who had been homeless for 2 years or more. Youths at the periphery were less likely to report unprotected intercourse and had been homeless for a shorter duration. Conclusions. HIV riskwas a function of risk-taking youths' connectionswith one another and was associated with position in the overall network structure. Social network-based prevention programs, young women's housing and health programs, and housing-first programs for peripheral youths could be effective strategies for preventing HIV among this population. | H57: United States | I57: 61 | J57: FALSE | K57: TRUE | L57: TRUE | M57: marginal | N57: TRUE | O57: Carefully worded but still a strong policy rec based on correlational analyses | Q57: TRUE | R57: =IF(Q57<>N57,"!!!","") | W57: TRUE
A58: SCOPUS_ID:85084695125 | B58: 10.1093/eurpub/ckaa031 | C58: Estonia advances on SDG achievement by tackling high alcohol consumption through a multi-pronged approach | D58: European Journal of Public Health | E58: 2020 | F58: [] | G58: Estonia has implemented a comprehensive, multipronged approach to the reduction of alcohol consumption in the population, comprising a series of successful policy responses. The Estonian alcohol strategy (2014) builds on the Global strategy to reduce the harmful use of alcohol and the European action plan to reduce the harmful use of alcohol 2012-2010. It aims to decrease the overall yearly consumption of alcohol among the adult population to less than 8 litres of absolute alcohol per capita. Gathering support across society from a range of stakeholders, including policy-makers, researchers, parents and advocates, has been one of the key elements in the implementation of the policy. High-level political commitment and strategic timing of efforts have maintained the issue of alcohol control on the political agenda and in the public's mind. | H58: Estonia | I58: 6 | J58: FALSE | K58: FALSE | L58: FALSE | M58: n/a it's a comment which describes past policy. Shouldn't be in the list but the filtering is imperfect | N58: FALSE | Q58: TRUE | R58: =IF(Q58<>N58,"!!!","") -> !!! | W58: TRUE
A59: SCOPUS_ID:0033557398 | B59: 10.1093/oxfordjournals.aje.a009814 | C59: Double-blind intervention trial on modulation of ozone effects on pulmonary function by antioxidant supplements | D59: American Journal of Epidemiology | E59: 1999 | F59: ['Antioxidants', 'Bicycling', 'Ozone', 'Spirometry', 'Vitamins'] | G59: The aim of this study was to investigate whether the acute effects of ozone on lung function could be modulated by antioxidant vitamin supplementation in a placebo-controlled study. Lung function was measured in Dutch bicyclists (n = 38) before and after each training session on a number of occasions (n = 380) during the summer of 1996. The vitamin group (n = 20) received 100 mg of vitamin E and 500 mg of vitamin C daily for 15 weeks. The average ozone concentration during exercise was 77 Î¼g/m3 (range, 14-186 Î¼g/m3). After exclusion of subjects with insufficient compliance from the analysis, a difference in ozone exposure of 100 Î¼g/m3 decreased forced expiratory volume in 1 second (FEV1) 95 ml (95% confidence interval (Cl) - 265 to -53) in the placebo group and 1 ml (95% Cl -94 to 132) in the vitamin group; for forced vital capacity, the change was -125 ml (95% Cl -384 to - 36) in the placebo group and -42 ml (95% Cl -130 to 35) in the vitamin group. The differences in ozone effect on lung function between the groups were statistically significant. The results suggest that supplementation with the antioxidant vitamins C and E confers partial protection against the acute effects of ozone on FEV1, and forced vital capacity in cyclists. | H59: Netherlands | I59: 72 | J59: FALSE | K59: FALSE | L59: FALSE | N59: FALSE | Q59: FALSE | R59: =IF(Q59<>N59,"!!!","") | W59: FALSE
A60: SCOPUS_ID:0033019577 | B60: 10.1136/jech.53.7.412 | C60: Determinants of self assessed health among Spanish older people living at home | D60: Journal of Epidemiology & Community Health | E60: 1999 | F60: [] | G60: Study objective - To identify the main determinants of self assessed health among community dwelling elderly. Participants and setting - A representative sample of 677 people aged 65 and over of the city of Madrid, Spain. Design - Cross sectional study. Information was collected through personal interviews at the homes of the selected subjects. The five category dependent variable was grouped into two categories: good and poor self assessed health. Age, sex, social class, use of physician services, number of chronic conditions, and functional capacity, were included as main explanatory factors. Adjusted odds ratios were estimated through multiple logistic regression models. Main results - A total of 49.5% of subjects rated their health as good or very good. Those aged 85 and over rated their health higher than those aged 65-74 (adjusted odds ratio (OR): 0.37; 95% confidence intervals (CI): 0.18, 0.77). The adjusted OR for an increase of three chronic conditions was 3.48 (95% CI: 2.49, 4.85). Functional capacity also showed a strong independent effect (OR: 3.64; 95% CI: 1.89, 7.02). Social class was one of the main determinants for the youngest group, with those in the upper class reporting a better health perception (OR: 3.28 95% CI: 1.70, 6.35), but showed no effect in the oldest old (OR: 1.05; 95% CI: 0.57, 1.96). Conclusions - Age, chronic conditions, and functional status were the main determinants of perceived health among Spanish elderly. The effect of social class on perceived health markedly decreases with age. This study may contribute to a better utilisation and interpretation of self ratings in research and in general practice. | H60: Spain | I60: 111 | J60: FALSE | K60: FALSE | L60: FALSE | N60: FALSE | Q60: FALSE | R60: =IF(Q60<>N60,"!!!","") | W60: FALSE
A61: SCOPUS_ID:78751685435 | B61: 10.1016/j.ypmed.2010.07.005 | C61: Screen time and risk behaviors in 10- to 16-year-old Canadian youth | D61: Preventive Medicine | E61: 2011 | F61: ['Adolescent', 'Computer', 'Risky behaviors', 'Television', 'Video games'] | G61: ObjectiveTo examine television, computer, and video game use as possible determinants of multiple risk behaviors (MRB) among Canadian youth. MethodsResults are based on the Canadian 2005/06 Health Behaviour in School-Aged Children Survey. This survey included a representative cross-sectional sample of 8215 youth in grades 6-10, and a 1-year longitudinal sample of 1424 youth in grades 9-10. Total hours per week of television, video games, and computer use were calculated and participants were grouped into quartiles. Six risk behavior variables (smoking, drunkenness, non-use of seatbelts, cannabis use, illicit drug use, non-use of condoms) were combined to form a MRB score. Ordinal and repeated measure logistic regression models were used to examine associations between screen time and MRB variables. ResultsHigh computer use (top quartile) was associated with approximately a 50% increased engagement of MRB in both samples. High television use was also associated with modestly increased engagement in MRB in the cross-sectional sample. ConclusionsHigh computer use was the screen time behavior that was mostly strongly and consistently associated with engagement in MRB. Future research is needed to understand the relationship between specific screen time behaviors and adolescent health to help strengthen current screen time guidelines for youth. Â© 2010. | H61: Canada | I61: 52 | J61: FALSE | K61: FALSE | L61: FALSE | N61: FALSE | Q61: FALSE | R61: =IF(Q61<>N61,"!!!","") | W61: FALSE
A62: SCOPUS_ID:33744471162 | B62: 10.1136/jech.2005.039032 | C62: Do perceptions of neighbourhood environment influence health? Baseline findings from a British survey of aging | D62: Journal of Epidemiology & Community Health | E62: 2006 | F62: [] | G62: Objectives: To investigate the relation between perceived neighbourhood environment, social contact and support, and self efficacy, on the health of older people. Design: British cross sectional population survey of people aged 65 and over. Participants: 999 people aged 65 plus living at home in Britain. Results: Regression modelling showed that high self efficacy had a strong independent association with better self rated health status and physical functioning. Indicators of perceived neighbourhood environment that showed strong associations with both good health and functioning were: perceptions of good quality facilities in the area (social/leisure, facilities for people aged 65+, rubbish collection, health services, transport, closeness to shops, somewhere nice to walk), and high levels of neighbourliness (knows/trusts people). Perceptions of problems in the area (noise, crime, air quality, rubbish/litter, traffic, graffiti) were also predictive of poorer health. Measures of social contact and support did not show any independent associations with health or functioning. Conclusions: The unique value of this paper is in the simultaneous analysis of associations between perceived neighbourhood, social contact and support, self efficacy, and health. The consistent strength of older people's perceptions of the quality of facilities in their neighbourhoods shows that responsive reinforcement of local infrastructures might have wider health benefits. Also of interest was the strength of self efficacy as a predictor of self rated health and physical functioning. The results have implications for both neighbourhood level interventions and self management programmes in chronic illness. | H62: United Kingdom | I62: 123 | J62: FALSE | K62: TRUE | L62: TRUE | M62: clear - broad but vague implications | N62: TRUE | O62: They talk about implications for… Might be stronger in the paper itself | Q62: TRUE | R62: =IF(Q62<>N62,"!!!","") | W62: TRUE
A63: SCOPUS_ID:84862587399 | B63: 10.2105/AJPH.2011.300408 | C63: Integrating biodiversity management and indigenous biopiracy protection to promote environmental justice and global health | D63: American Journal of Public Health | E63: 2012 | F63: [] | G63: Many potentially useful medicines arise from developing countries' biodiverse environments and indigenous knowledge. However, global intellectual property rules have resulted in biopiracy, raising serious ethical concerns of environmental justice, exploitation, and health disparities in these populations. Furthermore, state-based approaches have not led to adequate biodiversity protection,management, or resource sharing, which affect access to lifesaving drugs. In response, country delegates adopted the Nagoya Protocol, which aims at promoting biodiversity management, combating biopiracy, and encouraging equitable benefits sharing with indigenous communities. However, the effectiveness of this framework in meeting these objectives remains in question. To address these challenges, we propose a policy building on the Nagoya Protocol that employs a World Health Organization-World Trade Organization Joint Committee on Bioprospecting and Biopiracy. | H63: United States | I63: 25 | R63: =IF(Q63<>S63,"!!!","") -> !!! | S63: Review article | W63: TRUE
A64: SCOPUS_ID:2142711607 | B64: 10.1136/jech.2003.009852 | C64: Is perceived failure in school performance a trigger of physical injury? A case-crossover study of children in Stockholm County | D64: Journal of Epidemiology & Community Health | E64: 2004 | F64: [] | G64: Objectives: To investigate whether perceived failure in school performance increases the potential for children to be physically injured. Subjects: Children aged 10-15 years residing in the Stockholm County and hospitalised or called back for a medical check up because of a physical injury during the school years 2000-2001 and 2001-2002 (n=592). Methods: A case-crossover design was used and information on potential injury triggers was gathered by interview. Information about family socioeconomic circumstances was gathered by a questionnaire filled in by parents during the child interview (response rate 87%). Results: Perceived failure in school performance has the potential to trigger injury within up to 10 hours subsequent to exposure (relative risk=2.70; 95% confidence intervals=1.2 to 5.8). The risk is significantly higher among pre-adolescents and among children from families at a higher education level. Conclusions: Experiencing feelings of failure may affect children's physical safety, in particular among pre-adolescents. Possible mechanisms are perceptual deficits and response changes occasioned by the stress experienced after exposure. | H64: Sweden | I64: 8 | J64: FALSE | K64: FALSE | L64: FALSE | N64: FALSE | Q64: FALSE | R64: =IF(Q64<>N64,"!!!","") | W64: FALSE
A65: SCOPUS_ID:85047410366 | B65: 10.1097/EDE.0000000000000795 | C65: Diagnostic performance of one-off flexible sigmoidoscopy with fecal immunochemical testing in a large screening population | D65: Epidemiology | E65: 2018 | F65: [] | G65: Background: Flexible sigmoidoscopy and fecal immunochemical tests are established diagnostic tests for colorectal cancer (CRC) screening and less invasive, less expensive, and easier to conduct than colonoscopy. However, little is known about their joint diagnostic performance compared with colonoscopy. We aimed to assess the expected diagnostic performance of joint use of flexible sigmoidoscopy and fecal immunochemical test. Methods: We assessed the overall and site-specific prevalences of colorectal neoplasms and the overall sensitivity, specificity, area under the receiver operating characteristics curve of a quantitative fecal immunochemical test (FOB Gold, Sentinel Diagnostics, Milano, Italy) among 3,466 participants in screening colonoscopy in Germany. Results were used to model the expected diagnostic performance of joint use of flexible sigmoidoscopy and fecal immunochemical testing. Results: CRC and advanced adenomas were found in 29 (1%) and 354 (10%) participants, respectively. The area under the curve of fecal immunochemical testing for these outcomes could be raised from 96% to 100% and from 70% to 89%, respectively, by combining it with flexible sigmoidoscopy. At 90% specificity, sensitivity of fecal immunochemical testing would increase from 97% to 100% for CRC and from 40% to 79% for advanced adenomas. Conclusions: Combining flexible sigmoidoscopy and fecal immunochemical testing might strongly enhance diagnostic performance of each single test to a level close to the diagnostic performance of screening colonoscopy while avoiding many unnecessary colonoscopies. | H65: Germany | I65: 9 | J65: FALSE | K65: FALSE | L65: FALSE | N65: FALSE | Q65: FALSE | R65: =IF(Q65<>N65,"!!!","") | W65: FALSE
A66: SCOPUS_ID:76549115338 | B66: 10.1016/j.amepre.2009.10.040 | C66: Neighborhood, Route, and School Environments and Children's Active Commuting | D66: American Journal of Preventive Medicine | E66: 2010 | F66: [] | G66: Background: Walking and cycling to school represent an opportunity for children to achieve regular physical activity. These behaviors may be influenced by characteristics of the environment around homes and schools, yet few studies have quantified the potential associations between these two sets of factors. Purpose: This study aims to assess whether objectively measured characteristics of the neighborhood, route, and school environments are associated with active commuting to school among children, and it explores whether distance acts as a moderator in this association. Methods: A cross-sectional study was conducted of 2012 children (899 boys and 1113 girls) aged 9-10 years attending 92 schools in the county of Norfolk, United Kingdom. Questionnaires were completed by children and parents during Summer 2007. Attributes around the home and children's route to school were assessed using a GIS. School environments were assessed using a newly developed school audit and via questionnaires completed by head teachers. Data were analyzed in 2008. Results: Almost half of the children usually walked or cycled to school. Children who lived in a more deprived area and whose route to school was direct were less likely to walk or cycle to school, whereas those who had a higher density of roads in their neighborhood were more likely to walk. Further, children whose routes had a high density of streetlights were less likely to cycle to school. Distance did not moderate the observed associations. Conclusions: Objectively measured neighborhood and route factors are associated with walking and cycling to school. However, distance did not moderate the associations found here. Creating safe environments by improving urban design may influence children's commuting behavior. Intervention studies are needed to confirm the findings from this observational cross-sectional study. Â© 2010 American Journal of Preventive Medicine. | H66: United Kingdom | I66: 192 | J66: FALSE | K66: TRUE | L66: FALSE | M66: FALSE | N66: FALSE | O66: Calls for the development of interventions | Q66: TRUE | R66: =IF(Q66<>N66,"!!!","") -> !!! | S66: test if calling for interventions to test !=policy | W66: TRUE
A67: SCOPUS_ID:84905561636 | B67: 10.1097/EDE.0000000000000143 | C67: Long-term exposure to crystalline silica and risk of heart disease mortality | D67: Epidemiology | E67: 2014 | F67: [] | G67: BACKGROUND: The association between crystalline silica exposure and risk of heart disease mortality remains less clear. METHODS: We investigated a cohort of 42,572 Chinese workers who were potentially exposed to crystalline silica and followed from 1960 to 2003. Cumulative silica exposure was estimated by linking a job-exposure matrix to each person's work history. Low-level silica exposure was defined as never having held a job with an exposure higher than 0.1 mg/m. We estimated hazard ratios (HRs) in exposure-response analyses using Cox proportional hazards model. RESULTS: We identified 2846 deaths from heart disease during an average of 35 years follow-up. Positive exposure-response trends were observed for cumulative silica exposure associated with mortality from total heart disease (HRs for increasing quartiles of cumulative silica exposure compared with the unexposed group = 0.89, 1.09, 1.32, 2.10; P for linear trend < 0.001) and pulmonary heart disease (0.92, 1.39, 2.47, 5.46; P for linear trend < 0.001). These positive trends remained among workers with both high- and low-level silica exposure. There was also a positive trend for ischemic heart disease among workers with low-level exposure, with quartile HRs of 1.04, 1.13, 1.52, and 1.60 (P for linear trend < 0.001). CONCLUSION: Low-level crystalline silica exposure was associated with increased mortality from heart disease, including pulmonary heart disease and ischemic heart disease, whereas high-level exposure mainly increased mortality from pulmonary heart disease. Current permissible exposure limits for crystalline silica in many countries may be insufficient to protect people from deaths due to heart disease. Copyright Â© 2014 by Lippincott Williams & Wilkins. | H67: United States | I67: 30 | J67: FALSE | K67: TRUE | L67: FALSE | M67: marginal | N67: FALSE | O67: They call for new thresholds, which might be a concrete interventions? hard to call this one | P67: agree - The LLM gave good reasoning for this call when I asked it (It suggests that current regulatory standards ("permissible exposure limits") may need revision—a clear call for attention from policymakers or occupational safety regulators. | Q67: TRUE | R67: =IF(Q67<>N67,"!!!","") -> !!! | W67: TRUE
A68: SCOPUS_ID:18844403140 | B68: 10.1007/s10654-004-6880-1 | C68: The epidemiology of anophthalmia and microphthalmia in Sweden | D68: European Journal of Epidemiology | E68: 2005 | F68: ['Anophthalmia', 'Epidemiology', 'Maternal age', 'Microphthalmia', 'Smoking'] | G68: Infants with a clinical diagnosis of anophthalmia or microphthalmia were identified from four health registers in Sweden, covering different parts of the period 1965-2001. During the observation period, the rate of anophthalmia decreased from the early 1970s from 0.4 to 0.2 per 10,000 births. The registered rate of microphthalmia increased markedly during the observation period to reach a maximum in 1987 of about 1.5 per 10,000. About 10% of the 432 identified children had a chromosome anomaly. There was no geographical variation in prevalence and infants born in urban or rural districts had, if anything, a lower risk than infants born in cities (0.93 and 1.13 per 10,000, respectively). Non-eye malformations were more common at anophthalmia (63%) than at microphthalmia (30%). Sex ratio was normal and no statistically significant variation between sub-groups (anophthalmia, microphthalmia, isolated, associated with non-eye malformations) could be demonstrated. There was a marked risk increase with maternal age but no certain parity effect, no effect of maternal education, but a possible association with subfertility. Maternal smoking in early pregnancy seemed to increase the risk for anophthalmia or microphthalmia in the absence of a coloboma. Â© Springer 2005. | H68: Sweden | I68: 65 | J68: FALSE | K68: FALSE | L68: FALSE | N68: FALSE | Q68: FALSE | R68: =IF(Q68<>N68,"!!!","") | W68: FALSE
A69: SCOPUS_ID:0031028150 | B69: 10.1016/s0749-3797(18)30226-5 | C69: Representations of menopause and their health care implications: A qualitative study | D69: American Journal of Preventive Medicine | E69: 1997 | F69: [] | G69: Introduction: Menopause is primarily represented as a medical condition with its associated body changes described as symptoms in need of treatment. The purpose of this study was to determine whether women's representations of and responses to menopause reflected this medical perspective. It is based on a secondary analysis of data from an earlier study in which the menopause experience of 17 middle-aged women was examined. Methods: The original study used a qualitative methodology in which data were collected by means of semistructured interviews and then analyzed for primary categories of meaning. Interview transcripts were reanalyzed for the current study. Results: Findings of that analysis indicate that, although the women were relatively uninformed about menopause, they identified themselves as menopausal on the basis of both positively and negatively defined physical and psychological changes that they associated with it. These changes were also associated with aging in general. Furthermore, although the women responded to menopause as a time-limited physiological event that sometimes required medical attention, they perceived it primarily as a marker or symbol of more general life-stage developmental issues and responded with both lifestyle changes and a search for new meaning. Discussion: These findings indicate that the women's perception of and response to menopause reflected both medical and nonmedical representations. Health care implications include the importance of health care providers supporting menopausal women in their search for both information and meaning, and of researchers investigating both medical and nonmedical approaches to reducing the negative health- related effects of decreased estrogen levels in menopausal women. Medical Subject Headings (MESH): aging, climacteric, estrogen replacement therapy, health behavior, menopause. | H69: United States | I69: 20 | J69: FALSE | K69: TRUE | L69: TRUE | M69: clear | N69: TRUE | Q69: TRUE | R69: =IF(Q69<>N69,"!!!","") | W69: TRUE
A70: SCOPUS_ID:0030039192 | B70: 10.1093/ije/25.1.5 | C70: Cancer mortality among North African migrants in France | D70: International Journal of Epidemiology | E70: 1996 | F70: ['Cancer', 'Migrants', 'Mortality', 'North Africa', 'Relative risk'] | G70: Background. Data on cancer mortality in North African migrants to France (the largest foreign-born community in the country) are presented, providing useful insights both into cancer patterns in North Africa and their changes following migration. Methods. The cancer mortality in migrants from North Africa (Algeria, Morocco, Tunisia and Egypt) resident in France relative to that of the local-born population, is estimated from mortality data for the period 1979-1985, and population data from the 1982 French census. Risks of death from different cancers were adjusted for important confounding factors such as social status and area of residence. Results. The risks are quite similar for Algerian, Tunisian and Moroccan migrants. Compared to the local-born, those Maghrebian migrants of one or both sexes have higher risks of death from cancer of the nasopharynx, gallbladder and bladder (in Algerians only). Conversely, Maghrebian migrants have lower risks of death from cancer of the oral cavity, other pharynx, oesophagus, stomach, colon, rectum, lung, larynx, melanoma (in Algerians only), kidney and nervous system (except in Tunisians), breast, ovary, and cervix uteri (except in Moroccans). For Egyptian migrants, because of small numbers, few of the estimates are statistically significant. They are at lower risk of death from lung cancer and at higher risk for lymphoma and leukaemia. Conclusion. The findings provide confirmatory evidence of the unusual cancer patterns among North African populations, who have low risks for most cancer sites, and high risks for certain cancers, such as of the nasopharynx and bladder. | H70: Switzerland | I70: 46 | J70: FALSE | K70: FALSE | L70: FALSE | N70: FALSE | Q70: FALSE | R70: =IF(Q70<>N70,"!!!","") | W70: FALSE
A71: SCOPUS_ID:84902668737 | B71: 10.2105/AJPH.2014.301947 | C71: Gender-specific associations of objective and perceived neighborhood characteristics with body mass index and waist circumference among older adults in the English Longitudinal Study of Ageing | D71: American Journal of Public Health | E71: 2014 | F71: [] | G71: Objectives. We sought to determine whether objective and perceived neighborhood characteristics are independently associated with obesity indicators among older adults and whether associations differ by gender. Methods. Linear regression was used to examine mutually adjusted associations of objective area-level neighborhood deprivation and perceived individuallevel neighborhood disorder in 2002-2003 with body mass index (BMI) and waist circumference (WC) 2 years later among 6297 community-dwelling older adults in the English Longitudinal Study of Ageing. Results. Associations between neighborhood characteristics and obesity indicators were evident for women only. Being in the most deprived quintile of neighborhood deprivation was associated with a BMI that was 1.18 kilograms per meters squared higher (95% confidence interval [CI] = 0.54, 1.83) and a WC that was 2.42 centimeters higher (95% CI = 0.90, 3.94) at follow-up in women after adjustment for baseline health status, socioeconomic factors, and neighborhood disorder.Neighborhood disorder was not independently associated with BMI orWC. Conclusions. Among women, greater objective neighborhood deprivation was independently associated with higher BMI and WC after 2 years. Public efforts to reduce obesity among community-dwelling older women may benefit most from addressing objective residential characteristics, over and above subjective perceptions. | H71: United Kingdom | I71: 18 | J71: FALSE | K71: TRUE | L71: TRUE | M71: clear | N71: TRUE | Q71: TRUE | R71: =IF(Q71<>N71,"!!!","") | W71: TRUE
A72: SCOPUS_ID:0032914081 | B72: 10.1136/jech.53.6.348 | C72: Association between job characteristics and plasma fibrinogen in a normal working population: A cross sectional analysis in referents of the SHEEP study | D72: Journal of Epidemiology & Community Health | E72: 1999 | F72: [] | G72: Study objective - To explore the association between job characteristics and plasma fibrinogen concentrations. Design - Cross sectional design. Setting - The Greater Stockholm area. Subjects - A total of 1018 men and 490 women aged 45-70 who were randomly selected from the general population during 1992-1994. They were all employed and had no history of myocardial infarction. Main results - The self reported job characteristics were measured by a Swedish version of the Karasek demand-control questionnaire. For inferred scoring of job characteristics, psychosocial exposure categories (job control and psychological demands) were assigned by linking each subject's occupational history with a work organisation exposure matrix. Job strain was defined as the ratio between demands and control. In univariate analyses, expected linear trends were found in three of four tests of association between high plasma fibrinogen and low control (the self reported score for women and the inferred score for both sexes), in one of four tests of association between high plasma fibrinogen and high demands (the inferred score for women) and in two of four tests of association between high plasma fibrinogen and job strain (the inferred score for both sexes). Multiple logistic regression analyses showed that men in the inferred job strain group have an increased risk of falling into the increased plasma fibrinogen concentration group (above median level of the distribution) (odds ratio (OR) 1.2; 95% CI 1.0, 1.5) after adjustment for the variables that were associated with plasma fibrinogen in the univariate analyses. In women, low self reported control, high inferred demand, and inferred job strain were significantly associated with increased plasma fibrinogen concentration (OR 1.3; 95% CI 1.0, 1.8, OR 1.5; 95% CI 1.0, 2.2, OR 1.5; 95% CI 1.1, 2.2, respectively). Conclusions - These results indicate that adverse job characteristics may be related to plasma fibrinogen concentrations and this relation is more relevant in female workers. The clearest evidence for psychosocial effects on plasma fibrinogen seems to be with job control and the associations are clearer for the objective than for the self report variables. | H72: Sweden | I72: 49 | J72: FALSE | K72: FALSE | L72: FALSE | N72: FALSE | Q72: FALSE | R72: =IF(Q72<>N72,"!!!","") | W72: FALSE
A73: SCOPUS_ID:85005916303 | B73: 10.1016/j.amepre.2016.09.016 | C73: Association of Bacterial Vaginosis With Chlamydia and Gonorrhea Among Women in the U.S. Army | D73: American Journal of Preventive Medicine | E73: 2017 | F73: [] | G73: Introduction Bacterial vaginosis (BV) is a common vaginal condition in women of reproductive age, which has been associated with Chlamydia trachomatis and Neisseria gonorrhoeae among commercial sex workers and women attending sexually transmitted infection clinics. Pathogen-specific associations between BV and other sexually transmitted infections among U.S. military women have not been investigated. Methods A population-based, nested case-control study was conducted of all incident chlamydia and gonorrhea cases reported to the Defense Medical Surveillance System during 2006âˆ’2012. Using a density sampling approach, for each chlamydia or gonorrhea case, 10 age-matched (Â±1 year) controls were randomly selected from those women who were never diagnosed with these infections. Incidence rate ratios were estimated using conditional logistic regression. Statistical analysis was carried out in December 2015. Results A total of 37,149 chlamydia cases and 4,987 gonorrhea cases were identified during the study period. Antecedent BV was associated with an increased risk of subsequent chlamydia (adjusted incidence rate ratio=1.51; 95% CI=1.47, 1.55) and gonorrhea (adjusted incidence rate ratio=2.42; 95% CI=2.27, 2.57) infections. For every one additional episode of BV, the risk of acquiring chlamydia and gonorrhea infections increased by 13% and 26%, respectively. A monotonic doseâˆ’response relationship was also noted between antecedent BV and subsequent chlamydia and gonorrhea infection. In addition, an effect modification on the additive scale was found between BV and African-American race for gonorrhea, but not for chlamydia. Conclusions Among U.S. Army women, antecedent BV is associated with an increased risk of subsequent chlamydia and gonorrhea infection. | H73: United Kingdom | I73: 52 | J73: FALSE | K73: FALSE | L73: FALSE | N73: FALSE | Q73: FALSE | R73: =IF(Q73<>N73,"!!!","") | W73: FALSE
A74: SCOPUS_ID:0032440796 | B74: 10.2105/ajph.88.12.1846 | C74: Potential barriers to the removal of norplant among family planning clinic patients | D74: American Journal of Public Health | E74: 1998 | F74: [] | G74: Objectives. This study examined the prevalence and effects of potential barriers to removal of levonorgestrel implants (Norplant) among low-income women. Methods. A sample of 687 women who received Norplant at hospital- based family planning clinics were interviewed before Norplant insertion and 6 months after Norplant insertion (or at Norplant removal if removal occurred earlier). Those who continued to use Norplant were reinterviewed at 2 years or at removal. Results. In a multivariate analysis, only 1 of the 4 potential barriers - cost - significantly impeded Norplant discontinuation. Conclusions. Family planning clinics need to make clear that they follow a policy of Norplant removal on demand, regardless of the patient's ability to pay. | H74: United States | I74: 3 | J74: FALSE | K74: TRUE | L74: TRUE | M74: clear | N74: TRUE | Q74: TRUE | W74: TRUE
A75: SCOPUS_ID:0032694208 | B75: 10.1023/A:1007611412532 | C75: Osteoporosis and years since menopause | D75: European Journal of Epidemiology | E75: 1999 | F75: ['Bone mineral density (BMD)', 'Epidemiology', 'Osteoporosis', 'Years since menopause'] | G75: In Fukuoka Prefecture, in south-western Japan, a regional screening program for osteoporosis was conducted from 1994 to 1995. The screening level in the bone mineral density (BMD) at the distal non-dominant radius was equal to or less than two standard deviations below age-specific mean (â‰¤ -2.0 SD). In 1177 examinees with natural menopause (mean age: 61.4, range: 42-88), 56 of those who were screened were subsequently radiologically confirmed by orthopedic specialists to have osteoporosis (case group). They were then compared with 802 normal BMD (â‰¥ -1.0 SD) women (reference group) with their lifestyle and reproductive characteristics. The adjusted odds ratio (OR) and its 95% confidence interval (CI) were calculated using a logistic regression model. A significant increase in the ORs for osteoporosis based on the number of years since menopause was observed for 7-13 years since menopause (OR = 2.3; 95% CI: 1.0-5.4) compared with <7 years, however, no increasing trend in risk was evident in 14+ years since menopause (OR = 1.4; 95% CI: 0.4-5.1). Thus, the elevated risk continued up to around 10 years since menopause. These findings are consistent with previous studies that reported an alternation in the calcium metabolism and bone loss related to the length of time after menopause. Both the childhood and current milk consumption were also associated with a decreased risk: ORs were 0.4 (95% CI: 0.2-0.9) and 0.5 (95% CI: 0.3-1.0), respectively. | H75: Japan | I75: 8 | J75: FALSE | K75: FALSE | L75: FALSE | N75: FALSE | O75: Unclear whether the abstract is not truncated | Q75: FALSE | W75: FALSE
A76: SCOPUS_ID:0030850107 | B76: 10.2105/AJPH.87.6.1022 | C76: Prenatal health behaviors and psychosocial risk factors in pregnant women of mexican origin: The role of acculturation | D76: American Journal of Public Health | E76: 1997 | F76: [] | G76: Objectives. This study examined the association between acculturation of Mexican-origin women and factors in low birthweight and preterm delivery. Methods. Interviews were conducted with 911 Mexican-origin respondents in Los Angeles prenatal care clinics. Infant outcome data were retrieved from delivery records. Results. Mexican-American women had generally more undesirable prenatal behaviors mad risk factors than Mexican-immigrant women. Although higher acculturation was significantly associated with behavioral risk factors, there were no direct effects of acculturation on infant gestational age or birthweight. Conclusions. Future research needs to measure multiple factors to assess their effects on culture-specific protective factors. | H76: United States | I76: 199 | J76: FALSE | K76: FALSE | L76: FALSE | N76: FALSE | Q76: FALSE | W76: FALSE
A77: SCOPUS_ID:79960815320 | B77: 10.1093/aje/kwr086 | C77: Evaluating the incremental value of new biomarkers with integrated discrimination improvement | D77: American Journal of Epidemiology | E77: 2011 | F77: ['biological markers', 'bootstrap confidence interval', 'prediction', 'risk assessment', 'sampling distribution', 'sampling error', 'selection bias', 'type I error'] | G77: The integrated discrimination improvement (IDI) index is a popular tool for evaluating the capacity of a marker to predict a binary outcome of interest. Recent reports have proposed that the IDI is more sensitive than other metrics for identifying useful predictive markers. In this article, the authors use simulated data sets and theoretical analysis to investigate the statistical properties of the IDI. The authors consider the common situation in which a risk model is fitted to a data set with and without the new, candidate predictor(s). Results demonstrate that the published method of estimating the standard error of an IDI estimate tends to underestimate the error. The z test proposed in the literature for IDI-based testing of a new biomarker is not valid, because the null distribution of the test statistic is not standard normal, even in large samples. If a test for the incremental value of a marker is desired, the authors recommend the test based on the model. For investigators who find the IDI to be a useful measure, bootstrap methods may offer a reasonable option for inference when evaluating new predictors, as long as the added predictive capacity is large. Â© 2011 The Author. | H77: United States | I77: 167 | J77: FALSE | K77: FALSE | L77: FALSE | N77: FALSE | Q77: FALSE | W77: FALSE
A78: SCOPUS_ID:84880312110 | B78: 10.1016/j.amepre.2013.03.019 | C78: Challenges in cervical cancer prevention: A survey of U.S. Obstetrician-Gynecologists | D78: American Journal of Preventive Medicine | E78: 2013 | F78: [] | G78: Background Current cervical cancer prevention recommendations include human papillomavirus (HPV) vaccination, Pap and HPV co-testing, and Pap testing at 3- to 5-year intervals. Purpose To examine attitudes, practice patterns, and barriers related to HPV vaccination and cervical cancer screening guidelines among U.S. obstetrician-gynecologists. Methods In 2011-2012, a national sample of members of the American Congress of Obstetricians and Gynecologists responded to a 15-item (some with multiple parts) questionnaire assessing sociodemographic characteristics, clinical practices, and perceived barriers to HPV vaccination and cervical cancer screening. Multivariate logistic regression was used to identify factors associated with guideline adherence. Analyses were conducted in 2012. Results A total of 366 obstetrician-gynecologists participated. Ninety-two percent of respondents offered HPV vaccination to patients, but only 27% estimated that most eligible patients received vaccination. Parent and patient refusals were commonly cited barriers to HPV vaccination. Approximately half of respondents followed guidelines to begin cervical cancer screening at age 21 years, discontinue screening at age 70 years or after hysterectomy, and appropriately utilize Pap and HPV co-testing. Most physicians continued to recommend annual Paps (74% aged 21-29 years, 53% aged â‰¥30 years). Physicians felt that patients were uncomfortable with extended screening intervals and were concerned that patients would not come for annual exams without concurrent Paps. Solo practitioners were less likely to follow both vaccination and screening guidelines than those in group practices. Conclusions This survey of obstetrician-gynecologists indicates persistent barriers to the adoption of HPV vaccination and cervical cancer screening guidelines. Interventions to promote guideline adherence may help improve the quality of cervical cancer prevention. Â© 2013 American Journal of Preventive Medicine. | H78: United States | I78: 72 | J78: FALSE | K78: TRUE | L78: FALSE | M78: marginal | N78: TRUE | O78: I didnt not understand that they were calling for RCTs? | P78: LLM stated TRUE in latest prompt | Q78: TRUE | W78: TRUE
A79: SCOPUS_ID:79955779649 | B79: 10.1093/aje/kwq502 | C79: Dynamic path analysis in life-course epidemiology | D79: American Journal of Epidemiology | E79: 2011 | F79: ['blood pressure', 'body mass index', 'epidemiologic methods', 'heart diseases', 'path analysis', 'survival analysis'] | G79: Life-course epidemiology seeks to better understand the mechanisms that lead to the development of chronic diseases. An example is the mechanism leading from body size to coronary heart disease (CHD); one way to acquire a better understanding of this mechanism is to investigate to what extent it works through other risk factors. In this paper, the dynamic path analysis model is presented as a tool to analyze these dynamic mechanisms in life-course epidemiology. A key feature of dynamic path analysis is its ability to decompose the total effect of a risk factor into a direct effect (not mediated by other variables) and indirect effects (mediated through other variables). This is illustrated by examining the associations between repeated measurements of body mass index (BMI) and systolic blood pressure (SBP) and the risk of CHD in a sample of Danish men between 1976 and 2006. The effect of baseline BMI on the risk of CHD is decomposed into a direct effect and indirect effects going through later BMI, concurrent SBP, or later SBP. In conclusion, dynamic path analysis is a flexible tool that by the decomposition of effects can be used to increase the understanding of mechanisms that underlie the etiology of chronic disease. Â© The Author 2011. Published by Oxford University Press on behalf of the Johns Hopkins Bloomberg School of Public Health. All rights reserved. | H79: Denmark | I79: 19 | J79: FALSE | K79: FALSE | L79: FALSE | N79: FALSE | Q79: FALSE | W79: FALSE
A80: SCOPUS_ID:84907201782 | B80: 10.2105/AJPH.2013.301735 | C80: Factors influencing adoption of and adherence to indoor smoking bans among health disparity communities | D80: American Journal of Public Health | E80: 2014 | F80: [] | G80: Methods: We used a cross-sectional design to assess home smoking rules, smoking status, cigarettes smoked in the home, and barriers and benefits to attaining a smoke-free home among 138 caregivers (mean age = 30.0 years; 92% women) of children aged 0 to 6 years, between April 2010 and September 2012. Indoor SHS was assessed using a nicotine dosimeter. | H80: United States | I80: 12 | O80: Truncated abstract, I can only see the methods. | P80: latest filtering should remove | W80: FALSE
A81: SCOPUS_ID:0028282150 | B81: 10.1136/jech.48.2.188 | C81: Prevalence of total hip replacement: How much demand has been met? | D81: Journal of Epidemiology & Community Health | E81: 1994 | F81: [] | G81: Objective - To determine the prevalence of completed elective total hip replacements in a defined elderly population. Design - Cross sectional postal questionnaire survey with additional data and validation from general practice and hospital records. Setting - Six general practices in the English counties of Avon, Somerset, and Oxfordshire. Subjects - A total of 7806 patients aged 65 years and over (94.7% response). Results - The overall prevalence (95% confidence intervals) of elective total hip replacement was 5.3 (4.8, 5.8)%. Age and sex specific prevalences were 2.7 (2.0, 3.5)% in men and 4.1 (3.3, 4.9)% in women aged 65-74 years, and 5.2 (4.0, 6.5)% in men and 8.8 (7.6, 10.0)% in women aged 75 years and over. Of the 415 patients who had received elective total hip replacement, 28.2% had required bilateral surgery, 20% had received at least one operation privately, and 13% had required revision surgery. Conclusion - Our results show an increased level of satisfied demand for total hip replacement in elderly people compared with earlier estimates. The increasing prevalence of hip replacement is an indicator of increasing potential demand for revision procedures. Population based surveys are required to establish the level of unmet demand for primary procedures. Differences in past surgical activity may be important in interpreting the wide variation in current surgical rates. | H81: United Kingdom | I81: 27 | J81: FALSE | K81: FALSE | L81: FALSE | N81: FALSE | Q81: FALSE | W81: FALSE
A82: SCOPUS_ID:0026747758 | B82: 10.2105/AJPH.82.8.1133 | C82: Does equal socioeconomic status in Black and White men mean equal risk of mortality? | D82: American Journal of Public Health | E82: 1992 | F82: [] | G82: Although concerns have been expressed that mortality from coronary disease and all other causes is greater among Blacks than Whites, we hypothesized that, when socioeconomic status is adequately considered, mortality inequalities between Blacks and Whites are insignificant. The study population was a random sampling of Black and White men who were 35 years of age or older when recruited into the Charleston Heart Study in 1960. Education level and occupational status at baseline were used to compare mortality over the ensuing 28 years between Black and White men, who were classified as low or high socioeconomic status. In no instance were Black- White differences in all-cause or coronary disease mortality rates significantly different when socioeconomic status was controlled. We conclude that socioeconomic status is an important predictor of mortality and that, when socioeconomic status is considered, differences in Black-White mortality rates may be small. | H82: United States | I82: 97 | J82: FALSE | K82: FALSE | L82: FALSE | N82: FALSE | Q82: FALSE | W82: FALSE
A83: SCOPUS_ID:0029968968 | B83: 10.2105/AJPH.86.11.1607 | C83: Childhood victimization and subsequent risk for promiscuity, prostitution, and teenage pregnancy: A prospective study | D83: American Journal of Public Health | E83: 1996 | F83: [] | G83: Objectives. This study examined the extent to which being abused and/or neglected in childhood increases a person's risk for promiscuity, prostitution, and teenage pregnancy. Methods. A prospective cohorts design was used to match, on the basis of age, race, sex, and social class, cases of abused and/or neglected children from 1967 to 1971 with nonabused and nonneglected children; subjects were followed into young adulthood. From 1089 to 1995, 1196 subjects (676 abused and/or neglected and 520 control subjects) were located and interviewed. Results. Early childhood abuse and/or neglect was a significant predictor of prostitution for females (odds ratio [OR] = 2.96). For females, sexual abuse (OR = 2.54) and neglect (OR = 2.58) were associated with prostitution, whereas physical abuse was only marginally associated. Childhood abuse and neglect were not associated with increased risk for promiscuity or teenage pregnancy. Conclusions. These findings strongly support a relationship between childhood victimization and subsequent prostitution. The presumed causal sequence between childhood victimization and teenage pregnancy may need to be reevaluated. | H83: United States | I83: 300 | J83: FALSE | K83: FALSE | L83: FALSE | N83: FALSE | Q83: FALSE | W83: FALSE
A84: SCOPUS_ID:85055798363 | B84: 10.1093/aje/kwy158 | C84: The Number of Events per Confounder for Valid Estimation of Risk Difference Using Modified Least-Squares Regression | D84: American Journal of Epidemiology | E84: 2018 | F84: ['confounding', 'events per confounder', 'linear binomial model', 'modified least-squares regression', 'prenatal care', 'risk difference', 'simulation study'] | G84: Risk difference is a relevant effect measure in epidemiologic research. Although it is well known that when there are few events per confounder, logistic regression is not suitable for confounding control, it is not clear how many events per confounder are required for valid estimation of risk difference using linear binomial models. Because the maximum likelihood method has a convergence problem, we investigated the number of events per confounder necessary to validly estimate risk difference using modified least-squares regression in a simulation. We simulated 864 scenarios, according to the number of confounders (2-20), the number of events per confounder (2-12), marginal risk (0.5%-40%), exposure proportion (20% and 40%), and 3 sizes of risk difference. Our simulation showed that modified least-squares regression provided unbiased risk difference-regardless of the number of events per confounder-and reliable confidence intervals when more than 5 events were expected in the exposed and in the unexposed, irrespective of the number of events per confounder. We illustrated the modified least-squares regression analysis using perinatal epidemiologic data. Modified least-squares regression is considered to be a useful analytical tool for rare binary outcomes relative to the number of confounders. | H84: Japan | I84: 5 | J84: FALSE | K84: FALSE | L84: FALSE | N84: FALSE | Q84: FALSE | W84: FALSE
A85: SCOPUS_ID:84871232651 | B85: 10.1093/aje/kws212 | C85: Perinatal and family risk factors for Hodgkin lymphoma in childhood through young adulthood | D85: American Journal of Epidemiology | E85: 2012 | F85: ['birth order', 'family', 'fetal development', 'gestational age', 'Hodgkin disease', 'lymphoma', 'maternal age'] | G85: The incidence of Hodgkin lymphoma has increased among adolescents and young adults in recent decades, but the relevant risk factors in early life are still unknown. A national cohort study was conducted of 3,571,574 individuals born in Sweden in 1973-2008 and followed up for Hodgkin lymphoma incidence through 2009, to examine perinatal and family risk factors for Hodgkin lymphoma in childhood through young adulthood (ages 0-37 years). There were 943 Hodgkin lymphoma cases identified in 66.3 million person-years of follow-up. High fetal growth was associated with an increased risk of Hodgkin lymphoma after adjustment for gestational age at birth and other potential confounders (P trend = 0.005). Family history of Hodgkin lymphoma in a sibling or parent also was strongly associated with an increased risk, with adjusted hazard ratios = 8.83 (95% confidence interval: 3.67, 21.30) and 7.19 (95% confidence interval: 3.58, 14.44), respectively. No association was found between gestational age at birth, birth order, twinning, parental age, or parental education and Hodgkin lymphoma. These findings did not vary by age at Hodgkin lymphoma diagnosis. Similar associations were found for nodular sclerosis and mixed cellularity subtypes. These findings suggest that perinatal factors including possible growth factor pathways may contribute to the risk of Hodgkin lymphoma in childhood through young adulthood. Â© 2012 The Author. | H85: United States | I85: 51 | J85: FALSE | K85: FALSE | L85: FALSE | N85: FALSE | Q85: FALSE | W85: FALSE
A86: SCOPUS_ID:0034032147 | B86: 10.1023/A:1007621104789 | C86: Use of unconventional methods of therapy by cancer patients in Pakistan | D86: European Journal of Epidemiology | E86: 2000 | F86: ['Alternative medicine', 'Cancer patients', 'Developing countries', 'Unconventional medicine'] | G86: Most of the studies related to the use of unconventional methods of therapy by cancer patients have been carried out in the developed countries. This study was conducted to ascertain the frequency, type, and duration of use of unconventional methods of therapy by cancer patients in Pakistan. We also wanted to identify individuals who are most likely to use these methods and to compare the findings with those reported from the developed countries. Between 1 April and 30 May 1994, all patients with histologically proven cancer who visited the oncology unit were interviewed. A printed questionnaire with questions and options was used as an interview guide. Informed consent was obtained. One hundred and ninety-one patients were interviewed, on average, for 25 minutes each. Use of unconventional methods of therapy by cancer patients was widespread (54.5% of all patients). The majority (83.7%) were influenced by family members to use these methods. Traditional herbal medicines (70.2%) and homeopathy (64.4%) were the most commonly employed methods. Thirty-six percent of the users employed these methods before receiving any conventional therapy. Only 15% used these methods after conventional therapeutic options had been exhausted. Patients generally perceived these methods as useful, non-toxic and inexpensive. Age, marital status, socio-economic background, education level and status of underlying neoplasm did not influence the frequency of use of unconventional methods. The use, however, was influenced by gender, family size, and type of underlying malignancy. Patients aware of their diagnosis were less likely to use these methods. This study suggests that use of unconventional methods by cancer patients in Pakistan is widespread. Unlike western countries, these methods are often employed before receiving any conventional therapy. This probably results in a significant delay which can be expected to adversely influence the subsequent disease management and survival. Public education, reduction of cost and easy availability of conventional therapy may be helpful in reducing the use of methods which otherwise may have no proven value. | H86: Pakistan | I86: 39 | J86: FALSE | K86: TRUE | L86: FALSE | M86: marginal given it's a qual study, but doesn't directly make a policy claim? [on 2nd reading I could see this be TRUE, but I kept my original rating] | N86: TRUE | O86: It is vaguely worded but the last sentence calls for alternative policy focus, e.g. public educatino | P86: OK for discrepency if marginal | Q86: TRUE | W86: TRUE
A87: SCOPUS_ID:79960805262 | B87: 10.1093/aje/kwr074 | C87: Changes in the prevalence of cognitive impairment among older Americans, 1993-2004: Overall trends and differences by race/ethnicity | D87: American Journal of Epidemiology | E87: 2011 | F87: ['African Americans', 'aged', 'aged, 80 and over', 'cognition disorders', 'health status disparities', 'Hispanic Americans', 'prevalence', 'socioeconomic factors'] | G87: The authors used data from 6 waves of the Health and Retirement Study to evaluate changes in the prevalence of cognitive impairment among adults 70 years of age or older from 1993 to 2004. Having sampling weights for each wave enabled the authors to create merged waves that represented cross-sections of the community-dwelling older population for that year. Logistic regression analyses with year as the predictor were used to estimate trends and determine the contribution of sociodemographic and health status variables to decreasing trends in the prevalence of cognitive impairment over time (score â‰¤8 on a modified Telephone Interview Cognitive Screen). Results showed an annual decline in the prevalence of cognitive impairment of 3.4% after adjustment for age, gender, and prior test exposure (odds ratio (OR) = 0.966, 95% confidence interval (CI): 0.941, 0.992). The addition of socioeconomic variables to the model attenuated the trend by 72.1%. The annual percentage of decline in impairment was larger for blacks (OR = 0.943, 95% CI: 0.914, 0.973) and Hispanics (OR = 0.954, 95% CI: 0.912, 0.997) than for whites (OR = 0.971, 95% CI: 0.936, 1.006), although the differences were not statistically significant. Linear probability models used in secondary analyses showed larger percentage-point declines for blacks and Hispanics. Improvements in educational level contributed to declines in cognitive impairment among older adults - particularly blacks and Hispanics - in the United States. Â© 2011 The Author. | H87: United States | I87: 40 | J87: FALSE | K87: FALSE | L87: FALSE | N87: FALSE | Q87: FALSE | W87: FALSE
A88: SCOPUS_ID:85042868429 | B88: 10.1136/jech-2017-209333 | C88: Longitudinal analysis of cardiovascular disease risk profile in neighbourhood poverty subgroups: 5-year results from an afterschool fitness programme in the USA | D88: Journal of Epidemiology & Community Health | E88: 2018 | F88: ['cardiovascular disease', 'child health', 'health inequalities', 'physical activity', 'poverty'] | G88: Background The WHO calls for affordable populationbased prevention strategies for reducing the global burden of cardiovascular disease (CVD) on morbidity and mortality; however, effective, sustainable and accessible community-based approaches for CVD prevention in at-risk youth have yet to be identified. We examined the effects of implementing a daily park-based afterschool fitness programme on youth CVD risk profiles over 5 years and across area poverty subgroups. Methods The study included 2264 youth (mean age 9.4 years, 54% male, 50% Hispanic, 47% non-Hispanic black, 70% high/very high area poverty) in Miami, Florida, USA. We used three-level repeated measures mixed models to determine the longitudinal effects of programme participation on modifiable CVD outcomes (2010-2016). Results Duration of programme participation was significantly associated with CVD risk profile improvements, including body mass index (BMI) z-score, diastolic/systolic blood pressure, skinfold thicknesses, waist-hip ratio, sit-ups, push-ups, Progressive Aerobic Cardiovascular Endurance Run (PACER) score, 400 m run time, probability of developing systolic/diastolic hypertension and overweight/obesity in high/very high poverty neighbourhoods (P>0.001). Diastolic blood pressure decreased 3.4 percentile points (95% CI-5.85 to-0.85), 8.1 percentile points (95% CI-11.98 to-4.26), 6.1 percentile points (95% CI-11.49 to-0.66), 7.6 percentile points (95% CI-15.33 to-0.15) and 11.4 percentile points (95% CI-25.32 to 2.61) for 1-5 years, respectively, in high/very high poverty areas. In contrast, significant improvements were found only for PACER score and waist-hip ratio in low/mid poverty areas. Conclusion This analysis presents compelling evidence demonstrating that park-based afterschool programmes can successfully maintain or improve at-risk youth CVD profiles over multiple years. | H88: United States | I88: 19 | J88: FALSE | K88: FALSE | L88: FALSE | N88: TRUE | O88: Compelling evidence' for intervention | Q88: FALSE | W88: FALSE
A89: SCOPUS_ID:84929055179 | B89: 10.1093/eurpub/cku229 | C89: Comparing variation across European countries: Building geographical areas to provide sounder estimates | D89: European Journal of Public Health | E89: 2015 | F89: [] | G89: Background: In geographical studies, population distribution is a key issue. An unequal distribution across units of analysis might entail extra-variation and produce misleading conclusions on healthcare performance variations. This article aims at assessing the impact of building more homogeneous units of analysis in the estimation of systematic variation in three countries. Methods: Hospital discharges for six conditions (congestive heart failure, short-term complications of diabetes, hip fracture, knee replacement, prostatectomy in prostate cancer and percutaneous coronary intervention) produced in Denmark, England and Portugal in 2008 and 2009 were allocated to both original geographical units and new ad hoc areas. New areas were built using Ward's minimum variance methods. The impact of the new areas on variability was assessed using Kernel distribution curves and different statistic of variation such as Extremal Quotient, Interquartile Interval ratio, Systematic Component of Variation and Empirical Bayes statistic. Results: Ward's method reduced the number of areas, allowing a more homogeneous population distribution, yet 20% of the areas in Portugal exhibited less than 100 000 inhabitants vs. 7% in Denmark and 5% in England. Point estimates for Extremal Quotient and Interquartile Interval Ratio were lower in the three countries, particularly in less prevalent conditions. In turn, the Systematic Component of Variation and Empirical Bayes statistic were slightly lower in more prevalent conditions. Conclusions: Building new geographical areas produced a reduction of the variation in hospitalization rates in several prevalent conditions mitigating random noise, particularly in the smallest areas and allowing a sounder interpretation of the variation across countries. | H89: Spain | I89: 7 | J89: FALSE | K89: FALSE | L89: FALSE | N89: FALSE | Q89: FALSE | W89: FALSE
A90: SCOPUS_ID:0027940114 | B90: 10.1093/ije/23.4.673 | C90: No improvement in survival from melanoma diagnosed from 1973 to 1984 | D90: International Journal of Epidemiology | E90: 1994 | F90: [] | G90: Berwick M (Cancer Prevention Research Institute, 11 East 22nd Street, New York, NY 10010, USA), Dubin N, Luo S-T and Flannery J. No improvement in survival from melanoma diagnosed from 1973 to 1984. International Journal of Epidemiology 1994; 23: 673-681. Background. While the incidence and mortality of melanoma has increased dramatically during the last few decades, survival rates, based on the case-fatality ratio, have apparently improved. Efforts at early detection have probably been effective in the discovery of lesions at a curable stage. However, the effects of lead-time bias need to be accounted for in order to understand the contribution of early detection to the increased incidence. This can best be done by appropriately controlling for depth of the turnour or a surrogate of depth, at diagnosis. Methods. A survival analysis was conducted for 3197 Connecticut residents newly diagnosed with invasive melanoma between 1973 and 1984. Five prognostic variables were evaluated: sex, age at diagnosis, anatomical site, histological type, and year of diagnosis. Results. As expected, women and the young had better survival than men and the elderly. Melanomas located on the trunk had poorer prognosis than those on other sites. The survival experience by histological type was significantly different; lentigo maligna melanoma and superficial spreading melanoma had the best survival and nodular melanomas the poorest, while â€˜otherâ€™ and unclassifiable melanomas had intermediate survival. When survival by period of diagnosis was controlled by other variables, which included surrogates for disease stage, there was no improvement in survival over time. Conclusion. These data do not imply that early diagnosis and treatment are ineffective; rather, that within stages of disease, survival improvements did not occur during the period 1973-1984. Â© 1994 International Epidemiological Association. | H90: United States | I90: 9 | J90: FALSE | K90: FALSE | L90: FALSE | N90: FALSE | Q90: FALSE | R90: =IF(Q90<>N90,"!!!","") | W90: FALSE
A91: SCOPUS_ID:31944433220 | B91: 10.1007/s10654-005-4724-2 | C91: Characteristics and analysis of risk factors for mortality in infective endocarditis | D91: European Journal of Epidemiology | E91: 2006 | F91: ['Endocarditis', 'Haemodialysis', 'Mental alteration', 'Mortality', 'Prognosis', 'Vegetation'] | G91: Objective: The aim of our study was to establish the etiology of and risk factors for infective endocarditis (IE) and determine the prognostic factors for adverse outcome during hospital admission in a Turkish population. Material and Methods: Between January 2002 and January 2004, the clinical and laboratory features of 112 consecutive adult patients (>18 years) with diagnosis of IE who were referred to the infectious diseases clinics/departments of 17 teaching hospitals in Turkey were evaluated. Cases of IE were defined according to the modified Duke Criteria. Mortality was defined as death occurring within 30 days or during hospital stay period. Univariate and multivariate analyses were performed to predict the factors related to fatal outcome. Results: A total of 112 consecutive patients presented with 101 definite and 11 probable IE episodes were defined according to the modified Duke Criteria. The mean age was 45.2Â±19.9. Fifty percent of the patients were male. Ninety (60.4%) of the 112 patients had risk factors for IE and 48 (42.9%) of them had â‰¥2 risk factors. On the other hand, 49.1% of patients had cardiac risk factors. Blood cultures were positive in 94 (83.9%) cases. Staphylococci were the most common agents (50.0%), followed by streptococci (28.7%) and enterococi (16.0%). Native cardiac valves were detected in 93 (83%) of the episodes of suspected IE. Valvular involvement was present in 103 (92%) patients; the mitral valve, alone or in combination with other valves, was affected in 70 (62.5%) of the patients. Echocardiography detected vegetations in 105 patients (93.8%). The mortality rate was 28.6%. Three factors were independently associated with mortality: haemodialysis OR: 14.5 (95% CI: 1.5-138.2), mobile vegetation OR: 4.8 (95% CI: 1.5-15.4) and mental alteration OR: 4.1 (95% CI: 1.1-15.6). Conclusion: Mortality is still high in IE. Our data indicate that patients with altered mental status, mobile vegetation, or on haemodialysis had poorer prognosis. Â© Springer 2006. | H91: TÃ¼rkiye | I91: 48 | J91: FALSE | K91: FALSE | L91: FALSE | N91: FALSE | Q91: FALSE | R91: =IF(Q91<>N91,"!!!","") | W91: FALSE
A92: SCOPUS_ID:0025918863 | B92: 10.2105/AJPH.81.1.53 | C92: AIDS-related knowledge, sexual behavior, and condom use among men and women in Kinshasa, Zaire | D92: American Journal of Public Health | E92: 1991 | F92: [] | G92: This study was conducted in 1988 among a random sample of 6,625 men and women of reproductive age in all 24 administrative zones of Kinshasa, the capital city of Zaire, to determine existing levels of knowledge regarding AIDS (acquired immunodeficiency syndrome), sexual behavior, knowledge and use of condoms in marital and extramarital relations; perceived risk of AIDS, and attitudes toward testing for the human immunodeficiency virus (HIV). Awareness of AIDS is almost universal, and the vast majority know the four main modes of transmission. Almost half believed in transmission by mosquitoes and in a vaccine or cure for AIDS. The majority of male respondents knew of condoms, but negative attitudes toward condom use are widespread, and few respondents perceived them to play a central role in combatting AIDS. | H92: United States | I92: 39 | J92: FALSE | K92: FALSE | L92: FALSE | N92: FALSE | Q92: FALSE | R92: =IF(Q92<>N92,"!!!","") | W92: FALSE
A93: SCOPUS_ID:85207423519 | B93: 10.1136/jech-2024-222677 | C93: Association of housing tenure and unaffordable housing with preterm birth and other adverse birth outcomes in Canada: a population-based study | D93: Journal of Epidemiology & Community Health | E93: 2024 | F93: [] | G93: Background Socioeconomic risk factors are known drivers of adverse birth outcomes. Housing is a key target for policy interventions. Objective To estimate the associations of housing tenure (renting vs owning) and unaffordable housing with preterm birth and other adverse birth outcomes. Methods We used 2014â€“2016 Canadian birth registration data linked with the 2016 long-form census and included singleton births among homeowners and renters. Unaffordable housing was defined at the family level as the proportion of pre-tax income spent on shelter, using a 30% cut-off. The primary outcome was preterm birth. Secondary outcomes were stillbirth and infant death. Log-binomial regression estimated the association of housing tenure and unaffordability with outcomes adjusting for sociodemographic risk factors and parity. Results Among 162 700 live births and stillbirths (52 740 renters, 109 960 owners), 31% of renters and 17% of owners experienced unaffordable housing. Renting was associated with an increased risk of preterm birth (7.5% vs 6.1%; adjusted risk ratio (aRR) 1.13; 95% CI 1.08 to 1.17), stillbirth (9.5 vs 6.6 per 1000; aRR 1.33, 95% CI 1.14 to 1.56) and infant death (4.2 vs 3.0 per 1000; aRR 1.52, 95% CI 1.26 to 1.82). There was no association of housing unaffordability with preterm birth or other adverse birth outcomes among owners or renters. Conclusions This nationally representative study in Canada found associations between renting versus owning and preterm birth, stillbirth and infant death, as well as a high burden of unaffordable housing, particularly among renters. This study suggests that home tenure itself is a social determinant of adverse birth outcomes. | H93: Canada | I93: 0 | J93: FALSE | K93: FALSE | L93: FALSE | N93: FALSE | Q93: FALSE | W93: FALSE
A94: SCOPUS_ID:85108568071 | B94: 10.1136/jech-2021-216581 | C94: Effectiveness of the population-based a â‚¬ check your health preventive programme' conducted in a primary care setting: A pragmatic randomised controlled trial | D94: Journal of Epidemiology & Community Health | E94: 2022 | F94: ['epidemiology of chronic non communicable diseases', 'health promotion', 'prevention', 'treatment outcome'] | G94: Health checks have been suggested as an early detection approach aiming at lowering the risk of chronic disease development. This study aimed to evaluate the effectiveness of a health check programme offered to the general population, aged 30-49 years. Methods The entire population aged 30-49 years (N=26 216) living in the municipality of Randers, Denmark, was invited to a health check during 5 years. A pragmatic household cluster-randomised controlled trial was conducted in 10 505 citizens. The intervention group (IG, N=5250) included citizens randomised to the second year and reinvited in the 5th year. The comparison group (CG, N=5255) included citizens randomised to the 5th year. Outcomes were modelled cardiovascular disease (CVD) risk; self-reported physical activity (PA) and objectively measured cardio respiratory fitness (CRF); self-rated health (short-form 12 (SF-12)), self-rated mental health (SF-12_Mental Component Score (MCS)) and, registry information on sick-leave and employment. Due to low participation, we compared groups matched on propensity scores for participation when reinvited. Results Participation in the first health check was 51% (N=2698) in the IG and 40% (N=2120) in the CG. In the IG 26% (N=1340) participated in both the first and second health checks. No intervention effects were found comparing IG and CG. Mean differences were (95% CI): modelled CVD risk: -0.052 (95% CI -0.107 to 0.003)%, PA: -0.156 (-0.331 to 0.019) days/week with 30 min moderate PA, CRF: 0.133 (-0.560 to 0.826) mL O 2 /min/kg, SF-12: -0.003 (-0.032 to 0.026), SF-12_MCS: 0.355 (-0.423 to 1.132), sick leave periods â‰¥3 weeks: -0.004 (-0.025 to 0.017), employment: -0.004 (-0.032 to 0.024). Conclusions Preventive health checks offered to the general population, aged 30-49 years, had no effects on a wide range of indicators of chronic disease risk. Trial registration number NCT02028195. | H94: Denmark | I94: 2 | J94: FALSE | K94: FALSE | L94: FALSE | N94: TRUE | O94: Strong claim on effectiveness of intervention in RCT | Q94: FALSE | W94: FALSE
A95: SCOPUS_ID:84856106049 | B95: 10.1093/eurpub/ckq193 | C95: Prevalence and regional differences of gestational diabetes mellitus and oral glucose tolerance tests in Finland | D95: European Journal of Public Health | E95: 2012 | F95: [] | G95: Background: The prevalence of gestational diabetes (GDM) is constantly increasing all around the world. Aim of this study is to report prevalence and regional differences of GDM, oral glucose tolerance tests (OGTT) and register-based GDM risk factors [age and body mass index (BMI)] among Finnish women. Methods: Data from the Finnish Medical Birth Register including all deliveries in Finland during 2004-06 (N=174634) were used. The criteria for GDM were abnormal results in OGTT, GDM diagnosis based on ICD-10 classification or use of insulin treatment during pregnancy. Pregnant women with type I diabetes were excluded, but women with pregestational diabetes (type II) were included since they also can receive GDM diagnosis. Results: The prevalence of GDM was 10-11% and OGTTs 22-28% between the period 2004 until 2006. Regional differences were 2-fold both in prevalence of GDM (8-15%) and OGTTs (19-34%). Proportions of obese women varied between 28% and 35% and women aged >40 years between 3% and 4%. The regional differences in GDM prevalence were not attenuated when risk factors were taken into account. Overweight and age â‰¥years explained only a fourth of the variation in GDM prevalence. Conclusion: Proportion of women undergoing OGTT increased but the prevalence of GDM did not during the study period. Two-fold regional differences in OGTT prevalence explained higher proportion of variation in prevalence of GDM than risk factors available from birth registry, age and BMI. Â© The Author 2011. Published by Oxford University Press on behalf of the European Public Health Association. All rights reserved. | H95: Finland | I95: 20 | J95: FALSE | K95: FALSE | L95: FALSE | N95: FALSE | Q95: FALSE | W95: FALSE
A96: SCOPUS_ID:0842281637 | B96: 10.1016/j.ypmed.2003.11.003 | C96: Nicotine dependence, quit attempts, and quitting among smokers in a regional population sample from a country with a high prevalence of tobacco smoking | D96: Preventive Medicine | E96: 2004 | F96: ['Nicotine dependence', 'Quit attempts', 'Smoking', 'Smoking cessation'] | G96: Background. Nicotine dependence might function as a barrier to smoking cessation. Therefore, the goal was to determine whether single symptoms of nicotine dependence are related to the number of quit attempts and smoking status. Methods. In a random population sample of 4075 women and men aged 18-64, drawn from 47 German communities, data about nicotine dependence according to the US Diagnostic and Statistical Manual of Mental Disorders and according to the FagerstrÃ¶m Test for Nicotine Dependence (FTND), and data on quit attempts and quitting were collected at baseline with an interview and 30 months later with a questionnaire. Results. Nicotine dependence, in particular withdrawal, was related to a high number of quit attempts and to remaining a current smoker. The urgent need for tobacco, craving for nicotine, smoking to avoid withdrawal, and the expectation of increased appetite or weight gain correctly classified smoking status in 72.1% of individuals through logistic regression analysis. Conclusions. Nicotine dependence is a strong factor that may partly explain the failure of a subpopulation of smokers to live abstinent. Population-based interventions should include measures of tobacco control and brief interventions carried out, for example, by experts in health care. Â© 2003 The Institute For Cancer Prevention and Elsevier Inc. All rights reserved. | H96: Germany | I96: 82 | J96: FALSE | K96: TRUE | L96: TRUE | M96: clear | N96: TRUE | Q96: TRUE | W96: TRUE
A97: SCOPUS_ID:85142342895 | B97: 10.1016/j.ypmed.2022.107345 | C97: Total cost of care associated with opioid use disorder treatment | D97: Preventive Medicine | E97: 2023 | F97: ['Healthcare cost', 'Medicaid', 'Medication for opioid use disorder'] | G97: The opioid epidemic in the United States disproportionately affects Medicaid beneficiaries than other groups. This results in a significant financial burden on state Medicaid programs. In this analysis, we investigate the association of medication for opioid use disorder (MOUD) treatment initiation and linkage to ongoing care on overall healthcare costs of Medicaid Fee-for-Service patients. We conducted a retrospective study among adult patients diagnosed with opioid use disorder (OUD) and who had a clinical encounter at a safety-net institution in Denver Colorado in 2020. Three categories of MOUD status of patients were defined: 1) identified with OUD but did not receive MOUD; 2) initiated MOUD but not linked to ongoing treatment and 3) received MOUD and linked to ongoing treatment. Our outcome variable was per-member per-month total healthcare cost. We estimated a multivariable model to test the association between healthcare cost and MOUD status, while controlling for demographic and risk classification variables. We found that in individuals with OUD who initiated MOUD treatment but were not linked to ongoing care had the highest healthcare cost, while those who were linked to ongoing MOUD treatment had the lowest healthcare cost. MOUD treatment is not only effective at addressing the significant morbidity and mortality burden of OUD but also associated with decreased financial cost, which is disproportionately incurred by Medicaid. Additional policy and care delivery changes are needed to focus efforts to improve linkage to ongoing treatment. | H97: United States | I97: 2 | J97: FALSE | K97: TRUE | L97: TRUE | M97: marginal e.g., additional policy is required may be reasonable eg to solve an unresolved health issue | N97: TRUE | O97: Vaguely worded but calls for policy changes | Q97: TRUE | W97: TRUE
A98: SCOPUS_ID:0035038622 | B98: 10.2105/AJPH.91.5.761 | C98: Depression and substance use in minority middle-school students | D98: American Journal of Public Health | E98: 2001 | F98: [] | G98: Objectives: This study investigated the association between depression and substance use in a sample of middleschool students. Methods: The 5721 students (59%-63% Hispanic) completed self-report items on depressive symptoms, recent smoking and binge drinking, and lifetime use of marijuana, cocaine, and inhalants. Results: Symptoms of depression were strongly and positively related to substance use. For every type of use, a stepwise increase was seen between the percentage of students with low symptom frequency and the percentage of students with more symptoms. A sizable number of users reported symptoms indicating major depression. Depression scores showed few clinically meaningful differences among demographic subgroups. Substance use scores, in contrast; showed meaningful intergroup differences for racial/ethnic group and other demographic variables. Conclusions: Depressive symptoms and substance use were associated in a sample of middle-school students who were largely non-White and predominantly Hispanic. Greater understanding of the nature of this association is needed; this understanding should be used to design prevention programs, and prevention programs should be introduced at least in the middle-school years. | H98: United States | I98: 90 | J98: FALSE | K98: TRUE | L98: TRUE | M98: clear | N98: TRUE | Q98: TRUE | W98: TRUE
A99: SCOPUS_ID:33947211169 | B99: 10.1093/aje/kwk063 | C99: Smoking, hypertension, alcohol consumption, and risk of abdominal aortic aneurysm in men | D99: American Journal of Epidemiology | E99: 2007 | F99: ['Alcoholic beverages', 'Aorta', 'Aortic aneurysm', 'Ethanol', 'Risk factors', 'Smoking'] | G99: Despite the known protective association between moderate alcohol consumption and ischemic heart disease, little is known about the effects of alcohol consumption on abdominal aortic aneurysms (AAA). The authors analyzed prospective, biennially updated data for a cohort of 39,352 US men from 1986 to 2002. The association of incident AAA diagnosis with alcohol consumption in grams per day was assessed at baseline and by using alcohol consumption data updated every 4 years, controlling for previously reported cardiovascular risk factors. During 576,374 person-years of follow-up, 376 newly diagnosed cases of AAA were demonstrated. After adjustment for other risk factors for AAA, including smoking, hypertension, and body mass index, alcohol consumption at baseline was independently associated with AAA diagnosis (p for trend = 0.03), with a maximum hazard ratio of 1.21 (95% confidence interval: 0.78, 1.87) for â‰¥30.0 g (approximately â‰¥2 standard drinks) of daily alcohol consumption. This association was stronger when the updated alcohol consumption data were assessed rather than simply baseline exposure (p for trend = 0.02); the hazard ratio for the highest level of intake (â‰¥30.0 g/day) was 1.65 (95% confidence interval: 1.03, 2.64). Small numbers limited analyses by beverage type, but liquor demonstrated the strongest positive association with AAA. Copyright Â© 2007 by the Johns Hopkins Bloomberg School of Public Health All rights reserved. | H99: United States | I99: 81 | J99: FALSE | K99: FALSE | L99: FALSE | N99: FALSE | Q99: FALSE | W99: FALSE
A100: SCOPUS_ID:0036301558 | B100: 10.1093/ije/31.3.587 | C100: An ecologic study of protective equipment and injury in two contact sports | D100: International Journal of Epidemiology | E100: 2002 | F100: ['Football', 'Protective devices', 'Rugby Union', 'Sports injuries'] | G100: Background. Contact sports have high rates of injury. Protective equipment regulations are widely used as an intervention to reduce injury risk. The purpose of this study was to investigate the injury prevention effect of regulations governing protective equipment in two full-body contact sports. Methods. Injury rates in US collegiate football were compared to New Zealand club Rugby Union. Both sports involve significant body contact and have a high incidence of injury. Extensive body padding and hard-shell helmets are mandated in collegiate football but prohibited in Rugby Union. Results. The injury rate in football was approximately one-third the rugby rate (rate ratio [RR] = 0.35; 95% CI: 0.31-0.40). The head was the body site with the greatest differential in injury incidence (RR = 0.11; 95% CI: 0.08-0.16). Rugby players suffered numerous lacerations, abrasions, and contusions to the head region, but the incidence of these injuries in football was almost zero (RR = 0.01; 95% CI: 0.01-0.03). Injury rates were more similar for the knee (RR = 0.61; 95% CI: 0.43-0.87) and ankle (RR = 0.72; 95% CI: 0.46-1.13), two joints largely unprotected in both sports. Conclusions. The observed differences are consistent with the hypothesis that regulations mandating protective equipment reduce the incidence of injury, although important potential biases in exposure assessment cannot be excluded. Further research is needed into head protection for rugby players. | H100: United States | I100: 48 | J100: FALSE | K100: FALSE | L100: FALSE | N100: FALSE | Q100: FALSE | W100: FALSE
...

Sheet kappa
A1: Comparitors | C1: LLM vs EC | D1: terms vs EC | E1: DB vs EC
A2: n | C2: =ROWS(in!Q2:Q100) -> 99 | D2: =ROWS(in!J2:J100) -> 99 | E2: =ROWS(in!L2:L101) -> 100
A3: Matches | C3: {=SUMPRODUCT(--(in!Q2:Q100 = in!N2:N100))} -> 91 | D3: {=SUMPRODUCT(--(in!J2:J100 = in!O2:O100))} -> 73 | E3: {=SUMPRODUCT(--(in!L2:L101 = in!N2:N101))} -> 95
A4: Po | C4: =C3 / C2 -> 0.91919192 | D4: =D3 / D2 -> 0.73737374 | E4: =E3 / E2 -> 0.95
A5: p1_True | C5: =COUNTIF(in!Q2:Q100, TRUE) / C2 -> 0.23232323 | D5: =COUNTIF(in!Q2:Q100, TRUE) / D2 -> 0.23232323 | E5: =COUNTIF(in!L2:L101, TRUE) / E2 -> 0.17
A6: p1_False | C6: =COUNTIF(in!Q2:Q100, FALSE) / C2 -> 0.74747475 | D6: =COUNTIF(in!Q2:Q100, FALSE) / D2 -> 0.74747475 | E6: =COUNTIF(in!L2:L101, FALSE) / E2 -> 0.81
A7: p2_True | C7: =COUNTIF(in!N2:N100, TRUE) / C2 -> 0.19191919 | D7: =COUNTIF(in!N2:N100, TRUE) / D2 -> 0.19191919 | E7: =COUNTIF(in!N2:N101, TRUE) / E2 -> 0.2
A8: p2_False | C8: =COUNTIF(in!N2:N100, FALSE) / C2 -> 0.78787879 | D8: =COUNTIF(in!N2:N100, FALSE) / D2 -> 0.78787879 | E8: =COUNTIF(in!N2:N101, FALSE) / E2 -> 0.78
A9: Pe | C9: =C5 * C7 + C6 * C8 -> 0.63350679 | D9: =D5 * D7 + D6 * D8 -> 0.63350679 | E9: =E5 * E7 + E6 * E8 -> 0.6658
A10: Kappa | C10: =( C4 - C9 ) / ( 1 - C9 ) -> 0.77951002 | D10: =( D4 - D9 ) / ( 1 - D9 ) -> 0.28340757 | E10: =( E4 - E9 ) / ( 1 - E9 ) -> 0.85038899
A11: Kappa % | C11: =C10*100 -> 77.951002 | D11: =D10*100 -> 28.340757 | E11: =E10*100 -> 85.038899
C13: note, 1 abstract removed from sample as to small, thus 99
C14: sufficient for comparisons implausible to test for all
C15: clever selection of papers? So based on prior eg change across time or journal
